{"exportedAt":"2026-07-12T00:56:01.279Z","serverId":1003,"summary":{"players":49,"mapPlayers":49,"allianceMemberMergedPlayers":31,"mapOnlyPlayers":18,"noAlliancePlayers":5,"alliances":17,"allianceDetails":5,"activity":{"coreCount":17,"activeCount":13,"watchCount":14,"lowCount":0,"activeTotalCount":30},"allianceActivitySummary":{"coreAllianceCount":0,"activeAllianceCount":0,"watchAllianceCount":1,"lowAllianceCount":14,"insufficientAllianceCount":2,"activeAllianceCountForWar":0,"meaningfulAllianceCount":1},"serverActivity":{"grade":"QUIET","score":30,"reasons":["activeUserRate>=40%","activePowerRate>=65%"]},"serverActivitySummary":{"serverActivityGrade":"QUIET","serverActivityScore":30,"serverActivityReasons":["activeUserRate>=40%","activePowerRate>=65%"],"totalMapPlayers":49,"coreUsers":17,"activeGradeUsers":13,"watchGradeUsers":14,"lowGradeUsers":0,"activeUsers":31,"recentUsers":5,"sleepyUsers":5,"inactiveUsers":0,"quitLikelyUsers":0,"unknownStatusUsers":18,"activeUserRate":0.632653,"quitLikelyRate":0,"activeAllianceCountForWar":0,"meaningfulAllianceCount":1,"coreAllianceCount":0,"activeAllianceCount":0,"watchAllianceCount":1,"lowAllianceCount":14,"insufficientAllianceCount":2,"serverPowerTotal":1557578207,"activePowerTotal":1303527654,"activePowerRate":0.836894,"topAlliancePowerRate":0.536504,"top3AlliancePowerRate":0.781718},"userStatus":{"activeUsers":31,"recentUsers":5,"sleepyUsers":5,"inactiveUsers":0,"quitLikelyUsers":0,"unknownStatusUsers":18,"activeUserRate":0.632653,"quitLikelyRate":0},"activeAllianceCountForWar":0,"meaningfulAllianceCount":1,"excluded":"objects, objectsByType, allianceRepresentatives, member-only players"},"activityCriteria":{"grade":{"CORE":"activityScore >= 80","ACTIVE":"activityScore >= 50","WATCH":"activityScore >= 30","LOW":"activityScore < 30"},"score":{"map_found":30,"online":30,"recent_login_1d":25,"recent_login_3d":20,"recent_login_7d":10,"top_20_power":30,"top_50_power":15,"cumulative_power_80":25,"high_role":10,"alliance_member_confirmed":5},"note":"최종 대상은 지도에서 발견된 유저만 포함합니다. 길드원 목록에만 있는 유저는 보강용이며 최종 players에는 포함하지 않습니다."},"serverActivityCriteria":{"serverGrade":{"VERY_ACTIVE":"serverActivityScore >= 80","ACTIVE":"serverActivityScore >= 60","NORMAL":"serverActivityScore >= 40","QUIET":"serverActivityScore >= 20","DEAD":"serverActivityScore < 20"},"userStatus":{"ACTIVE":"online or lastLogin <= 1 day","RECENT":"lastLogin <= 3 days","SLEEPY":"lastLogin <= 7 days","INACTIVE":"lastLogin > 7 days or > 14 days","QUIT_LIKELY":"lastLogin > 30 days or > 14 days and not allianceMember confirmed","UNKNOWN":"lastLogin missing"}},"players":[{"uid":"378839118940","username":"أبومروان","nickname":"أبومروان","serverId":1003,"worldId":1,"x":392,"y":654,"pointId":335045,"pointType":1,"level":100,"power":79741680,"armyPower":"3,439,532,370,602,908,000,000,000,000,000,000,000","armyPowerText":"3.44hh","allianceId":"100218933","allianceTag":"h3R0","allianceName":"Order of Heros","allianceRole":5,"rank":5,"isOnline":0,"joinTime":1760703028,"lastShowTime":1783813147,"lastLogin":1783813147,"language":"ar","nationalflag":-1,"gender":0,"usergender":1,"headFrameId":0,"source":{"map":true,"allianceMember":true},"powerRankInAlliance":1,"powerPercentileInAlliance":0.05,"powerContributionRate":0.095425,"cumulativePowerContributionRate":0.095425,"activityScore":115,"activityReasons":["map_found","top_20_power","cumulative_power_80","recent_login_1d","alliance_member_confirmed"],"activityGrade":"CORE","userStatus":"ACTIVE","inactiveScore":0,"inactiveReasons":["lastLoginWithin1Day"],"lastLoginDaysAgo":0.05},{"uid":"388049368253","username":"Paladin","nickname":"Paladin","serverId":1003,"worldId":1,"x":383,"y":645,"pointId":330432,"pointType":1,"level":100,"power":71153132,"armyPower":"3,100,434,428,514,848,000,000,000,000,000,000,000","armyPowerText":"3.1hh","allianceId":"100218933","allianceTag":"h3R0","allianceName":"Order of Heros","allianceRole":4,"rank":4,"isOnline":0,"joinTime":1764013934,"lastShowTime":1783814842,"lastLogin":1783814842,"language":"en","nationalflag":233,"gender":0,"usergender":0,"headFrameId":2,"source":{"map":true,"allianceMember":true},"powerRankInAlliance":2,"powerPercentileInAlliance":0.1,"powerContributionRate":0.085147,"cumulativePowerContributionRate":0.180572,"activityScore":125,"activityReasons":["map_found","top_20_power","cumulative_power_80","recent_login_1d","high_role","alliance_member_confirmed"],"activityGrade":"CORE","userStatus":"ACTIVE","inactiveScore":0,"inactiveReasons":["lastLoginWithin1Day"],"lastLoginDaysAgo":0.03},{"uid":"403747300521","username":"XxcougxX","nickname":"XxcougxX","serverId":1003,"worldId":1,"x":401,"y":659,"pointId":337609,"pointType":1,"level":100,"power":65889214,"armyPower":"911,096,726,724,605,800,000,000,000,000,000,000","armyPowerText":"911gg","allianceId":"100218933","allianceTag":"h3R0","allianceName":"Order of Heros","allianceRole":4,"rank":4,"isOnline":0,"joinTime":1695426295,"lastShowTime":1783461052,"lastLogin":1783461052,"language":"en","nationalflag":233,"gender":0,"usergender":1,"headFrameId":0,"source":{"map":true,"allianceMember":true},"powerRankInAlliance":3,"powerPercentileInAlliance":0.15,"powerContributionRate":0.078848,"cumulativePowerContributionRate":0.259421,"activityScore":110,"activityReasons":["map_found","top_20_power","cumulative_power_80","recent_login_7d","high_role","alliance_member_confirmed"],"activityGrade":"CORE","userStatus":"SLEEPY","inactiveScore":35,"inactiveReasons":["lastLoginWithin7Days"],"lastLoginDaysAgo":4.13},{"uid":"497436881630","username":"扇風機","nickname":"扇風機","serverId":1003,"worldId":1,"x":382,"y":654,"pointId":335040,"pointType":1,"level":100,"power":64433331,"armyPower":"966,653,219,378,469,200,000,000,000,000,000,000","armyPowerText":"967gg","allianceId":"100218933","allianceTag":"h3R0","allianceName":"Order of Heros","allianceRole":3,"rank":3,"isOnline":0,"joinTime":1764061095,"lastShowTime":1783786472,"lastLogin":1783786472,"language":"jp","nationalflag":114,"gender":0,"usergender":2,"headFrameId":48,"source":{"map":true,"allianceMember":true},"powerRankInAlliance":4,"powerPercentileInAlliance":0.2,"powerContributionRate":0.077106,"cumulativePowerContributionRate":0.336527,"activityScore":125,"activityReasons":["map_found","top_20_power","cumulative_power_80","recent_login_1d","high_role","alliance_member_confirmed"],"activityGrade":"CORE","userStatus":"ACTIVE","inactiveScore":0,"inactiveReasons":["lastLoginWithin1Day"],"lastLoginDaysAgo":0.36},{"uid":"382760150153","username":"ZackTom","nickname":"ZackTom","serverId":1003,"worldId":1,"x":419,"y":293,"pointId":150226,"pointType":1,"level":100,"power":60805849,"armyPower":"2,769,959,312,811,832,600,000,000,000,000,000,000","armyPowerText":"2.77hh","allianceId":"100215856","allianceTag":"RaVa","allianceName":"RAVAGERS","allianceRole":6,"rank":6,"isOnline":0,"joinTime":1715680255,"lastShowTime":1783813486,"lastLogin":1783813486,"language":"en","nationalflag":233,"gender":0,"usergender":0,"headFrameId":2,"source":{"map":true,"allianceMember":true},"powerRankInAlliance":1,"powerPercentileInAlliance":0.25,"powerContributionRate":0.341072,"cumulativePowerContributionRate":0.341072,"activityScore":100,"activityReasons":["map_found","top_50_power","cumulative_power_80","recent_login_1d","alliance_member_confirmed"],"activityGrade":"CORE","userStatus":"ACTIVE","inactiveScore":0,"inactiveReasons":["lastLoginWithin1Day"],"lastLoginDaysAgo":0.05},{"uid":"325075411709","username":"EZAir","nickname":"EZAir","serverId":1003,"worldId":1,"x":422,"y":298,"pointId":152788,"pointType":1,"level":100,"power":60286062,"armyPower":"2,099,875,296,491,627,800,000,000,000,000,000,000","armyPowerText":"2.1hh","allianceId":"100215856","allianceTag":"RaVa","allianceName":"RAVAGERS","allianceRole":5,"rank":5,"isOnline":0,"joinTime":1690429118,"lastShowTime":1783816346,"lastLogin":1783816346,"language":"en","nationalflag":240,"gender":0,"usergender":1,"headFrameId":49,"source":{"map":true,"allianceMember":true},"powerRankInAlliance":2,"powerPercentileInAlliance":0.5,"powerContributionRate":0.338157,"cumulativePowerContributionRate":0.679229,"activityScore":100,"activityReasons":["map_found","top_50_power","cumulative_power_80","recent_login_1d","alliance_member_confirmed"],"activityGrade":"CORE","userStatus":"ACTIVE","inactiveScore":0,"inactiveReasons":["lastLoginWithin1Day"],"lastLoginDaysAgo":0.02},{"uid":"401227523344","username":"Neil","nickname":"Neil","serverId":1003,"worldId":1,"x":465,"y":453,"pointId":232169,"pointType":1,"level":100,"power":59084302,"armyPower":"1,871,604,508,700,720,700,000,000,000,000,000,000","armyPowerText":"1.87hh","allianceId":"100216886","allianceTag":"UDs1","allianceName":"Underdogs 1","allianceRole":6,"rank":6,"isOnline":0,"joinTime":1747591449,"lastShowTime":1783797096,"lastLogin":1783797096,"language":"en","nationalflag":77,"gender":0,"usergender":1,"headFrameId":114,"source":{"map":true,"allianceMember":true},"powerRankInAlliance":1,"powerPercentileInAlliance":0.2,"powerContributionRate":0.290111,"cumulativePowerContributionRate":0.290111,"activityScore":115,"activityReasons":["map_found","top_20_power","cumulative_power_80","recent_login_1d","alliance_member_confirmed"],"activityGrade":"CORE","userStatus":"ACTIVE","inactiveScore":0,"inactiveReasons":["lastLoginWithin1Day"],"lastLoginDaysAgo":0.24},{"uid":"393350673616","username":"😈YARA😈","nickname":"😈YARA😈","serverId":1003,"worldId":1,"x":390,"y":656,"pointId":336068,"pointType":1,"level":100,"power":55838413,"armyPower":"1,628,524,268,932,027,400,000,000,000,000,000,000","armyPowerText":"1.63hh","allianceId":"100218933","allianceTag":"h3R0","allianceName":"Order of Heros","allianceRole":7,"rank":7,"isOnline":0,"joinTime":1783802197,"lastShowTime":1783807188,"lastLogin":1783807188,"language":"ar","nationalflag":183,"gender":0,"usergender":2,"headFrameId":159,"source":{"map":true,"allianceMember":true},"powerRankInAlliance":5,"powerPercentileInAlliance":0.25,"powerContributionRate":0.066821,"cumulativePowerContributionRate":0.403347,"activityScore":100,"activityReasons":["map_found","top_50_power","cumulative_power_80","recent_login_1d","alliance_member_confirmed"],"activityGrade":"CORE","userStatus":"ACTIVE","inactiveScore":0,"inactiveReasons":["lastLoginWithin1Day"],"lastLoginDaysAgo":0.12},{"uid":"382948332633","username":"wifey","nickname":"wifey","serverId":1003,"worldId":1,"x":216,"y":580,"pointId":297069,"pointType":1,"level":100,"power":53199266,"armyPower":"2,423,660,383,383,237,000,000,000,000,000,000,000","armyPowerText":"2.42hh","allianceId":"100218933","allianceTag":"h3R0","allianceName":"Order of Heros","allianceRole":3,"rank":3,"isOnline":0,"joinTime":1764030866,"lastShowTime":1783462319,"lastLogin":1783462319,"language":"en","nationalflag":233,"gender":0,"usergender":2,"headFrameId":3,"source":{"map":true,"allianceMember":true},"powerRankInAlliance":6,"powerPercentileInAlliance":0.3,"powerContributionRate":0.063662,"cumulativePowerContributionRate":0.46701,"activityScore":95,"activityReasons":["map_found","top_50_power","cumulative_power_80","recent_login_7d","high_role","alliance_member_confirmed"],"activityGrade":"CORE","userStatus":"SLEEPY","inactiveScore":35,"inactiveReasons":["lastLoginWithin7Days"],"lastLoginDaysAgo":4.11},{"uid":"386017612969","username":"Zanga","nickname":"Zanga","serverId":1003,"worldId":1,"x":372,"y":656,"pointId":336059,"pointType":1,"level":100,"power":53060137,"armyPower":"3,369,864,033,855,192,000,000,000,000,000,000,000","armyPowerText":"3.37hh","allianceId":"100218933","allianceTag":"h3R0","allianceName":"Order of Heros","allianceRole":3,"rank":3,"isOnline":0,"joinTime":1689104611,"lastShowTime":1783787199,"lastLogin":1783787199,"language":"en","nationalflag":233,"gender":0,"usergender":1,"headFrameId":159,"source":{"map":true,"allianceMember":true},"powerRankInAlliance":7,"powerPercentileInAlliance":0.35,"powerContributionRate":0.063496,"cumulativePowerContributionRate":0.530505,"activityScore":110,"activityReasons":["map_found","top_50_power","cumulative_power_80","recent_login_1d","high_role","alliance_member_confirmed"],"activityGrade":"CORE","userStatus":"ACTIVE","inactiveScore":0,"inactiveReasons":["lastLoginWithin1Day"],"lastLoginDaysAgo":0.35},{"uid":"379178230873","username":"syberdx","nickname":"syberdx","serverId":1003,"worldId":1,"x":384,"y":640,"pointId":327873,"pointType":1,"level":100,"power":52941301,"armyPower":"2,189,268,030,608,134,800,000,000,000,000,000,000","armyPowerText":"2.19hh","allianceId":"100218933","allianceTag":"h3R0","allianceName":"Order of Heros","allianceRole":3,"rank":3,"isOnline":0,"joinTime":1783261439,"lastShowTime":1783788038,"lastLogin":1783788038,"language":"fr","nationalflag":38,"gender":0,"usergender":1,"headFrameId":4,"source":{"map":true,"allianceMember":true},"powerRankInAlliance":8,"powerPercentileInAlliance":0.4,"powerContributionRate":0.063354,"cumulativePowerContributionRate":0.593859,"activityScore":110,"activityReasons":["map_found","top_50_power","cumulative_power_80","recent_login_1d","high_role","alliance_member_confirmed"],"activityGrade":"CORE","userStatus":"ACTIVE","inactiveScore":0,"inactiveReasons":["lastLoginWithin1Day"],"lastLoginDaysAgo":0.34},{"uid":"384899474599","username":"RedWolf","nickname":"RedWolf","serverId":1003,"worldId":1,"x":459,"y":461,"pointId":236262,"pointType":1,"level":100,"power":51656980,"armyPower":"1,733,670,545,703,359,000,000,000,000,000,000,000","armyPowerText":"1.73hh","allianceId":"100216886","allianceTag":"UDs1","allianceName":"Underdogs 1","allianceRole":5,"rank":5,"isOnline":0,"joinTime":1647391126,"lastShowTime":1783798408,"lastLogin":1783798408,"language":"en","nationalflag":233,"gender":0,"usergender":1,"headFrameId":68,"source":{"map":true,"allianceMember":true},"powerRankInAlliance":2,"powerPercentileInAlliance":0.4,"powerContributionRate":0.253642,"cumulativePowerContributionRate":0.543753,"activityScore":100,"activityReasons":["map_found","top_50_power","cumulative_power_80","recent_login_1d","alliance_member_confirmed"],"activityGrade":"CORE","userStatus":"ACTIVE","inactiveScore":0,"inactiveReasons":["lastLoginWithin1Day"],"lastLoginDaysAgo":0.22},{"uid":"325914616585","username":"山🐺𝖑𝖋","nickname":"山🐺𝖑𝖋","serverId":1003,"worldId":17,"x":758,"y":732,"pointId":375164,"pointType":1,"level":100,"power":49923153,"armyPower":"1,676,984,224,035,742,000,000,000,000,000,000,000","armyPowerText":"1.68hh","allianceId":"100218933","allianceTag":"h3R0","allianceName":"Order of Heros","allianceRole":3,"rank":3,"isOnline":0,"joinTime":1764033447,"lastShowTime":1783635654,"lastLogin":1783635654,"language":"en","nationalflag":104,"gender":0,"usergender":1,"headFrameId":8,"source":{"map":true,"allianceMember":true},"powerRankInAlliance":9,"powerPercentileInAlliance":0.45,"powerContributionRate":0.059742,"cumulativePowerContributionRate":0.653601,"activityScore":105,"activityReasons":["map_found","top_50_power","cumulative_power_80","recent_login_3d","high_role","alliance_member_confirmed"],"activityGrade":"CORE","userStatus":"RECENT","inactiveScore":10,"inactiveReasons":["lastLoginWithin3Days"],"lastLoginDaysAgo":2.11},{"uid":"522696491846","username":"upgrade","nickname":"upgrade","serverId":1003,"worldId":1,"x":380,"y":648,"pointId":331967,"pointType":1,"level":100,"power":45870485,"armyPower":"601,805,286,080,155,160,000,000,000,000,000,000","armyPowerText":"602gg","allianceId":"100218933","allianceTag":"h3R0","allianceName":"Order of Heros","allianceRole":3,"rank":3,"isOnline":0,"joinTime":1695554967,"lastShowTime":1783602757,"lastLogin":1783602757,"language":"en","nationalflag":158,"gender":0,"usergender":0,"headFrameId":49,"source":{"map":true,"allianceMember":true},"powerRankInAlliance":10,"powerPercentileInAlliance":0.5,"powerContributionRate":0.054892,"cumulativePowerContributionRate":0.708493,"activityScore":105,"activityReasons":["map_found","top_50_power","cumulative_power_80","recent_login_3d","high_role","alliance_member_confirmed"],"activityGrade":"CORE","userStatus":"RECENT","inactiveScore":10,"inactiveReasons":["lastLoginWithin3Days"],"lastLoginDaysAgo":2.49},{"uid":"382263293043","username":"wy.382263293043","nickname":"wy.382263293043","serverId":1003,"worldId":1,"x":648,"y":140,"pointId":72005,"pointType":1,"level":100,"power":43466631,"armyPower":"843,016,691,694,492,700,000,000,000,000,000,000","armyPowerText":"843gg","allianceId":"300109845","allianceTag":"|qCg","allianceName":"WYG3822","allianceRole":5,"rank":5,"isOnline":0,"joinTime":1640847957,"lastShowTime":1783722168,"lastLogin":1783722168,"language":"en","nationalflag":13,"gender":0,"usergender":1,"headFrameId":0,"source":{"map":true,"allianceMember":true},"powerRankInAlliance":1,"powerPercentileInAlliance":1,"powerContributionRate":1,"cumulativePowerContributionRate":1,"activityScore":55,"activityReasons":["map_found","recent_login_3d","alliance_member_confirmed"],"activityGrade":"ACTIVE","userStatus":"RECENT","inactiveScore":10,"inactiveReasons":["lastLoginWithin3Days"],"lastLoginDaysAgo":1.11},{"uid":"364415120363","username":"Camokid","nickname":"Camokid","serverId":1003,"worldId":1,"x":468,"y":910,"pointId":466155,"pointType":1,"level":100,"power":42474499,"armyPower":"976,274,651,062,976,800,000,000,000,000,000,000","armyPowerText":"976gg","allianceId":"100181606","allianceTag":"WECU","allianceName":"Band of Misfit","allianceRole":5,"rank":5,"isOnline":0,"joinTime":1722051158,"lastShowTime":1783756319,"lastLogin":1783756319,"language":"en","nationalflag":233,"gender":0,"usergender":0,"headFrameId":1,"source":{"map":true,"allianceMember":true},"powerRankInAlliance":1,"powerPercentileInAlliance":1,"powerContributionRate":1,"cumulativePowerContributionRate":1,"activityScore":60,"activityReasons":["map_found","recent_login_1d","alliance_member_confirmed"],"activityGrade":"ACTIVE","userStatus":"ACTIVE","inactiveScore":0,"inactiveReasons":["lastLoginWithin1Day"],"lastLoginDaysAgo":0.71},{"uid":"392807290073","username":"jadenko","serverId":1003,"worldId":1003,"x":355,"y":487,"pointId":249522,"pointType":1,"level":100,"power":42419263,"armyPower":"1,791,444,553,435,583,500,000,000,000,000,000,000","armyPowerText":"1.79hh","allianceId":"100237028","allianceTag":"WAL!","language":"es","nationalflag":49,"gender":0,"usergender":0,"source":{"map":true},"powerRankInAlliance":1,"powerPercentileInAlliance":1,"powerContributionRate":1,"cumulativePowerContributionRate":1,"activityScore":30,"activityReasons":["map_found"],"activityGrade":"WATCH","userStatus":"UNKNOWN","inactiveScore":0,"inactiveReasons":["lastLogin_unknown"],"lastLoginDaysAgo":null},{"uid":"331587916585","username":"Dre","nickname":"Dre","serverId":1003,"worldId":1,"x":376,"y":660,"pointId":338109,"pointType":1,"level":100,"power":40034177,"armyPower":"1,684,174,823,027,166,500,000,000,000,000,000,000","armyPowerText":"1.68hh","allianceId":"100218933","allianceTag":"h3R0","allianceName":"Order of Heros","allianceRole":3,"rank":3,"isOnline":0,"joinTime":1688129356,"lastShowTime":1783808987,"lastLogin":1783808987,"language":"en","nationalflag":233,"gender":0,"usergender":0,"headFrameId":48,"source":{"map":true,"allianceMember":true},"powerRankInAlliance":11,"powerPercentileInAlliance":0.55,"powerContributionRate":0.047908,"cumulativePowerContributionRate":0.756401,"activityScore":95,"activityReasons":["map_found","cumulative_power_80","recent_login_1d","high_role","alliance_member_confirmed"],"activityGrade":"CORE","userStatus":"ACTIVE","inactiveScore":0,"inactiveReasons":["lastLoginWithin1Day"],"lastLoginDaysAgo":0.1},{"uid":"329648481062","username":"Prime","nickname":"Prime","serverId":1003,"worldId":1,"x":387,"y":645,"pointId":330434,"pointType":1,"level":100,"power":38284145,"armyPower":"784,913,701,517,736,600,000,000,000,000,000,000","armyPowerText":"785gg","allianceId":"100218933","allianceTag":"h3R0","allianceName":"Order of Heros","allianceRole":2,"rank":2,"isOnline":0,"joinTime":1694563508,"lastShowTime":1783775948,"lastLogin":1783775948,"language":"en","nationalflag":38,"gender":0,"usergender":1,"headFrameId":0,"source":{"map":true,"allianceMember":true},"powerRankInAlliance":12,"powerPercentileInAlliance":0.6,"powerContributionRate":0.045814,"cumulativePowerContributionRate":0.802215,"activityScore":70,"activityReasons":["map_found","recent_login_1d","high_role","alliance_member_confirmed"],"activityGrade":"ACTIVE","userStatus":"ACTIVE","inactiveScore":0,"inactiveReasons":["lastLoginWithin1Day"],"lastLoginDaysAgo":0.48},{"uid":"401245492496","username":"seewolf","nickname":"seewolf","serverId":1003,"worldId":1,"x":392,"y":262,"pointId":134341,"pointType":1,"level":100,"power":37018143,"armyPower":"386,857,957,368,053,040,000,000,000,000,000,000","armyPowerText":"387gg","allianceId":"100216886","allianceTag":"UDs1","allianceName":"Underdogs 1","allianceRole":4,"rank":4,"isOnline":0,"joinTime":1741645865,"lastShowTime":1783360623,"lastLogin":1783360623,"language":"de","nationalflag":57,"gender":0,"usergender":1,"headFrameId":2,"source":{"map":true,"allianceMember":true},"powerRankInAlliance":3,"powerPercentileInAlliance":0.6,"powerContributionRate":0.181763,"cumulativePowerContributionRate":0.725516,"activityScore":80,"activityReasons":["map_found","cumulative_power_80","recent_login_7d","high_role","alliance_member_confirmed"],"activityGrade":"CORE","userStatus":"SLEEPY","inactiveScore":35,"inactiveReasons":["lastLoginWithin7Days"],"lastLoginDaysAgo":5.29},{"uid":"384857568423","username":"wy.384857568423","nickname":"wy.384857568423","serverId":1003,"worldId":1,"x":472,"y":446,"pointId":228589,"pointType":1,"level":100,"power":34844405,"armyPower":"1,070,607,890,379,558,800,000,000,000,000,000,000","armyPowerText":"1.07hh","allianceId":"100216886","allianceTag":"UDs1","allianceName":"Underdogs 1","allianceRole":8,"rank":8,"isOnline":1,"joinTime":1720059837,"lastShowTime":1783817665,"lastLogin":1783817665,"language":"en","nationalflag":233,"gender":0,"usergender":0,"headFrameId":0,"source":{"map":true,"allianceMember":true},"powerRankInAlliance":4,"powerPercentileInAlliance":0.8,"powerContributionRate":0.17109,"cumulativePowerContributionRate":0.896606,"activityScore":90,"activityReasons":["map_found","online","recent_login_1d","alliance_member_confirmed"],"activityGrade":"CORE","userStatus":"ACTIVE","inactiveScore":0,"inactiveReasons":["online"],"lastLoginDaysAgo":0},{"uid":"385800615081","username":"oGFightR","nickname":"oGFightR","serverId":1003,"worldId":1,"x":291,"y":543,"pointId":278162,"pointType":1,"level":100,"power":34618020,"armyPower":"1,090,609,961,158,869,500,000,000,000,000,000,000","armyPowerText":"1.09hh","allianceId":"100218933","allianceTag":"h3R0","allianceName":"Order of Heros","allianceRole":2,"rank":2,"isOnline":0,"joinTime":1681150101,"lastShowTime":1783574391,"lastLogin":1783574391,"language":"en","nationalflag":233,"gender":0,"usergender":1,"headFrameId":72,"source":{"map":true,"allianceMember":true},"powerRankInAlliance":13,"powerPercentileInAlliance":0.65,"powerContributionRate":0.041427,"cumulativePowerContributionRate":0.843642,"activityScore":65,"activityReasons":["map_found","recent_login_3d","high_role","alliance_member_confirmed"],"activityGrade":"ACTIVE","userStatus":"RECENT","inactiveScore":10,"inactiveReasons":["lastLoginWithin3Days"],"lastLoginDaysAgo":2.82},{"uid":"386239513770","username":"JAGUAR","serverId":1003,"worldId":1003,"x":226,"y":122,"pointId":62578,"pointType":1,"level":100,"power":33980342,"armyPower":"300,024,738,723,586,800,000,000,000,000,000,000","armyPowerText":"300gg","allianceId":"300101839","allianceTag":"edg2","language":"es","nationalflag":174,"gender":0,"usergender":1,"source":{"map":true},"powerRankInAlliance":1,"powerPercentileInAlliance":1,"powerContributionRate":1,"cumulativePowerContributionRate":1,"activityScore":30,"activityReasons":["map_found"],"activityGrade":"WATCH","userStatus":"UNKNOWN","inactiveScore":0,"inactiveReasons":["lastLogin_unknown"],"lastLoginDaysAgo":null},{"uid":"386363016362","username":"paul","nickname":"paul","serverId":1003,"worldId":1,"x":390,"y":638,"pointId":326852,"pointType":1,"level":100,"power":32812380,"armyPower":"1,359,472,712,593,514,200,000,000,000,000,000,000","armyPowerText":"1.36hh","allianceId":"100218933","allianceTag":"h3R0","allianceName":"Order of Heros","allianceRole":3,"rank":3,"isOnline":0,"joinTime":1764003052,"lastShowTime":1783804369,"lastLogin":1783804369,"language":"en","nationalflag":233,"gender":0,"usergender":0,"headFrameId":69,"source":{"map":true,"allianceMember":true},"powerRankInAlliance":14,"powerPercentileInAlliance":0.7,"powerContributionRate":0.039266,"cumulativePowerContributionRate":0.882908,"activityScore":70,"activityReasons":["map_found","recent_login_1d","high_role","alliance_member_confirmed"],"activityGrade":"ACTIVE","userStatus":"ACTIVE","inactiveScore":0,"inactiveReasons":["lastLoginWithin1Day"],"lastLoginDaysAgo":0.16},{"uid":"388216702141","username":"michael","nickname":"michael","serverId":1003,"worldId":1,"x":382,"y":650,"pointId":332992,"pointType":1,"level":100,"power":31323395,"armyPower":"1,845,160,915,302,032,000,000,000,000,000,000,000","armyPowerText":"1.85hh","allianceId":"100218933","allianceTag":"h3R0","allianceName":"Order of Heros","allianceRole":3,"rank":3,"isOnline":0,"joinTime":1766457242,"lastShowTime":1783814146,"lastLogin":1783814146,"language":"en","nationalflag":233,"gender":0,"usergender":1,"headFrameId":44,"source":{"map":true,"allianceMember":true},"powerRankInAlliance":15,"powerPercentileInAlliance":0.75,"powerContributionRate":0.037484,"cumulativePowerContributionRate":0.920392,"activityScore":70,"activityReasons":["map_found","recent_login_1d","high_role","alliance_member_confirmed"],"activityGrade":"ACTIVE","userStatus":"ACTIVE","inactiveScore":0,"inactiveReasons":["lastLoginWithin1Day"],"lastLoginDaysAgo":0.04},{"uid":"323741217530","username":"karonte","nickname":"karonte","serverId":1003,"worldId":1,"x":418,"y":298,"pointId":152786,"pointType":1,"level":100,"power":29301310,"armyPower":"209,288,866,587,975,600,000,000,000,000,000,000","armyPowerText":"209gg","allianceId":"100215856","allianceTag":"RaVa","allianceName":"RAVAGERS","allianceRole":8,"rank":8,"isOnline":0,"joinTime":1698448655,"lastShowTime":1783269909,"lastLogin":1783269909,"language":"es","nationalflag":157,"gender":0,"usergender":1,"headFrameId":0,"source":{"map":true,"allianceMember":true},"powerRankInAlliance":3,"powerPercentileInAlliance":0.75,"powerContributionRate":0.164357,"cumulativePowerContributionRate":0.843586,"activityScore":45,"activityReasons":["map_found","recent_login_7d","alliance_member_confirmed"],"activityGrade":"WATCH","userStatus":"SLEEPY","inactiveScore":35,"inactiveReasons":["lastLoginWithin7Days"],"lastLoginDaysAgo":6.34},{"uid":"400957682960","username":"Chefkev","nickname":"Chefkev","serverId":1003,"worldId":1,"x":420,"y":294,"pointId":150739,"pointType":1,"level":100,"power":27885352,"armyPower":"239,742,401,016,961,600,000,000,000,000,000,000","armyPowerText":"240gg","allianceId":"100215856","allianceTag":"RaVa","allianceName":"RAVAGERS","allianceRole":3,"rank":3,"isOnline":0,"joinTime":1776186742,"lastShowTime":1783641485,"lastLogin":1783641485,"language":"en","nationalflag":233,"gender":0,"usergender":1,"headFrameId":0,"source":{"map":true,"allianceMember":true},"powerRankInAlliance":4,"powerPercentileInAlliance":1,"powerContributionRate":0.156414,"cumulativePowerContributionRate":1,"activityScore":65,"activityReasons":["map_found","recent_login_3d","high_role","alliance_member_confirmed"],"activityGrade":"ACTIVE","userStatus":"RECENT","inactiveScore":10,"inactiveReasons":["lastLoginWithin3Days"],"lastLoginDaysAgo":2.04},{"uid":"392869688537","username":"Eldyll","serverId":1003,"worldId":1003,"x":720,"y":572,"pointId":293225,"pointType":1,"level":100,"power":26525829,"armyPower":"259,151,552,647,106,100,000,000,000,000,000,000","armyPowerText":"259gg","allianceId":"100234927","allianceTag":"]CW[","language":"es","nationalflag":182,"gender":0,"usergender":0,"source":{"map":true},"powerRankInAlliance":1,"powerPercentileInAlliance":1,"powerContributionRate":1,"cumulativePowerContributionRate":1,"activityScore":30,"activityReasons":["map_found"],"activityGrade":"WATCH","userStatus":"UNKNOWN","inactiveScore":0,"inactiveReasons":["lastLogin_unknown"],"lastLoginDaysAgo":null},{"uid":"318912533195","username":"Butinski","serverId":1003,"worldId":1003,"x":770,"y":402,"pointId":206210,"pointType":1,"level":80,"power":23801146,"armyPower":"52,726,522,151,781,735,000,000,000,000","armyPowerText":"52.7ee","language":"en","nationalflag":233,"gender":0,"usergender":1,"source":{"map":true},"userStatus":"UNKNOWN","inactiveScore":0,"inactiveReasons":["lastLogin_unknown"],"lastLoginDaysAgo":null},{"uid":"382173742195","username":"wy.382173742195","serverId":1003,"worldId":1003,"x":99,"y":635,"pointId":325170,"pointType":1,"level":100,"power":23409911,"armyPower":"50,871,765,877,423,660,000,000,000,000,000,000","armyPowerText":"50.9gg","allianceId":"100214794","allianceTag":"GWRP","language":"en","nationalflag":233,"gender":0,"usergender":0,"source":{"map":true},"powerRankInAlliance":1,"powerPercentileInAlliance":1,"powerContributionRate":1,"cumulativePowerContributionRate":1,"activityScore":30,"activityReasons":["map_found"],"activityGrade":"WATCH","userStatus":"UNKNOWN","inactiveScore":0,"inactiveReasons":["lastLogin_unknown"],"lastLoginDaysAgo":null},{"uid":"364146873323","username":"Charlie6","serverId":1003,"worldId":1003,"x":199,"y":521,"pointId":266852,"pointType":1,"level":100,"power":23337375,"armyPower":"66,025,996,189,194,480,000,000,000,000,000,000","armyPowerText":"66gg","allianceId":"100198341","allianceTag":"WR1$","language":"en","nationalflag":233,"gender":0,"usergender":1,"source":{"map":true},"powerRankInAlliance":1,"powerPercentileInAlliance":1,"powerContributionRate":1,"cumulativePowerContributionRate":1,"activityScore":30,"activityReasons":["map_found"],"activityGrade":"WATCH","userStatus":"UNKNOWN","inactiveScore":0,"inactiveReasons":["lastLogin_unknown"],"lastLoginDaysAgo":null},{"uid":"385079854247","username":"WCA","nickname":"WCA","serverId":1003,"worldId":1,"x":472,"y":450,"pointId":230637,"pointType":1,"level":100,"power":21057342,"armyPower":"253,640,183,213,635,070,000,000,000,000,000,000","armyPowerText":"254gg","allianceId":"100216886","allianceTag":"UDs1","allianceName":"Underdogs 1","allianceRole":4,"rank":4,"isOnline":0,"joinTime":1703797252,"lastShowTime":1783812067,"lastLogin":1783812067,"language":"es","nationalflag":182,"gender":0,"usergender":1,"headFrameId":69,"source":{"map":true,"allianceMember":true},"powerRankInAlliance":5,"powerPercentileInAlliance":1,"powerContributionRate":0.103394,"cumulativePowerContributionRate":1,"activityScore":70,"activityReasons":["map_found","recent_login_1d","high_role","alliance_member_confirmed"],"activityGrade":"ACTIVE","userStatus":"ACTIVE","inactiveScore":0,"inactiveReasons":["lastLoginWithin1Day"],"lastLoginDaysAgo":0.07},{"uid":"384568669325","username":"GATES","nickname":"GATES","serverId":1003,"worldId":1,"x":310,"y":264,"pointId":135324,"pointType":1,"level":83,"power":18954853,"armyPower":"827,209,940,610,875,000,000,000,000,000","armyPowerText":"827ee","allianceId":"100218933","allianceTag":"h3R0","allianceName":"Order of Heros","allianceRole":3,"rank":3,"isOnline":0,"joinTime":1752030924,"lastShowTime":1783349462,"lastLogin":1783349462,"language":"en","nationalflag":233,"gender":0,"usergender":1,"headFrameId":50,"source":{"map":true,"allianceMember":true},"powerRankInAlliance":16,"powerPercentileInAlliance":0.8,"powerContributionRate":0.022683,"cumulativePowerContributionRate":0.943074,"activityScore":55,"activityReasons":["map_found","recent_login_7d","high_role","alliance_member_confirmed"],"activityGrade":"ACTIVE","userStatus":"SLEEPY","inactiveScore":35,"inactiveReasons":["lastLoginWithin7Days"],"lastLoginDaysAgo":5.42},{"uid":"383116391562","username":"TheWolf","serverId":1003,"worldId":1003,"x":748,"y":650,"pointId":333175,"pointType":1,"level":85,"power":18885510,"armyPower":"7,174,376,714,360,580,000,000,000,000,000","armyPowerText":"7.17ff","allianceId":"100251205","allianceTag":"~JZb","language":"en","nationalflag":233,"gender":0,"usergender":1,"source":{"map":true},"powerRankInAlliance":1,"powerPercentileInAlliance":1,"powerContributionRate":1,"cumulativePowerContributionRate":1,"activityScore":30,"activityReasons":["map_found"],"activityGrade":"WATCH","userStatus":"UNKNOWN","inactiveScore":0,"inactiveReasons":["lastLogin_unknown"],"lastLoginDaysAgo":null},{"uid":"379219932249","username":"ENO","nickname":"ENO","serverId":1003,"worldId":1,"x":374,"y":648,"pointId":331964,"pointType":1,"level":85,"power":17212837,"armyPower":"961,899,806,519,036,300,000,000,000,000","armyPowerText":"962ee","allianceId":"100218933","allianceTag":"h3R0","allianceName":"Order of Heros","allianceRole":3,"rank":3,"isOnline":0,"joinTime":1764819431,"lastShowTime":1783739606,"lastLogin":1783739606,"language":"en","nationalflag":233,"gender":0,"usergender":0,"headFrameId":0,"source":{"map":true,"allianceMember":true},"powerRankInAlliance":17,"powerPercentileInAlliance":0.85,"powerContributionRate":0.020598,"cumulativePowerContributionRate":0.963673,"activityScore":70,"activityReasons":["map_found","recent_login_1d","high_role","alliance_member_confirmed"],"activityGrade":"ACTIVE","userStatus":"ACTIVE","inactiveScore":0,"inactiveReasons":["lastLoginWithin1Day"],"lastLoginDaysAgo":0.9},{"uid":"381506385010","username":"FrankN","serverId":1003,"worldId":1003,"x":493,"y":635,"pointId":325367,"pointType":1,"level":100,"power":16065769,"armyPower":"165,653,993,512,546,270,000,000,000,000,000,000","armyPowerText":"166gg","allianceId":"100215290","allianceTag":"krj1","language":"en","nationalflag":233,"gender":0,"usergender":0,"source":{"map":true},"powerRankInAlliance":1,"powerPercentileInAlliance":1,"powerContributionRate":1,"cumulativePowerContributionRate":1,"activityScore":30,"activityReasons":["map_found"],"activityGrade":"WATCH","userStatus":"UNKNOWN","inactiveScore":0,"inactiveReasons":["lastLogin_unknown"],"lastLoginDaysAgo":null},{"uid":"385674220713","username":"Brad","serverId":1003,"worldId":1003,"x":808,"y":414,"pointId":212373,"pointType":1,"level":80,"power":14899435,"armyPower":"99,623,207,278,653,730,000,000,000,000","armyPowerText":"99.6ee","language":"en","nationalflag":233,"gender":0,"usergender":1,"source":{"map":true},"userStatus":"UNKNOWN","inactiveScore":0,"inactiveReasons":["lastLogin_unknown"],"lastLoginDaysAgo":null},{"uid":"382761337993","username":"AvrgeBrw","nickname":"AvrgeBrw","serverId":1003,"worldId":1,"x":389,"y":643,"pointId":329411,"pointType":1,"level":87,"power":14842747,"armyPower":"22,316,124,625,573,200,000,000,000,000,000","armyPowerText":"22.3ff","allianceId":"100218933","allianceTag":"h3R0","allianceName":"Order of Heros","allianceRole":3,"rank":3,"isOnline":0,"joinTime":1775751106,"lastShowTime":1783783776,"lastLogin":1783783776,"language":"en","nationalflag":233,"gender":0,"usergender":0,"headFrameId":4,"source":{"map":true,"allianceMember":true},"powerRankInAlliance":18,"powerPercentileInAlliance":0.9,"powerContributionRate":0.017762,"cumulativePowerContributionRate":0.981435,"activityScore":70,"activityReasons":["map_found","recent_login_1d","high_role","alliance_member_confirmed"],"activityGrade":"ACTIVE","userStatus":"ACTIVE","inactiveScore":0,"inactiveReasons":["lastLoginWithin1Day"],"lastLoginDaysAgo":0.39},{"uid":"330565641000","username":"👽_BB_👽","serverId":1003,"worldId":1003,"x":669,"y":155,"pointId":79695,"pointType":1,"level":100,"power":12554772,"armyPower":"4,012,426,261,546,339,000,000,000,000,000,000","armyPowerText":"4.01gg","language":"en","nationalflag":13,"gender":0,"usergender":1,"source":{"map":true},"userStatus":"UNKNOWN","inactiveScore":0,"inactiveReasons":["lastLogin_unknown"],"lastLoginDaysAgo":null},{"uid":"384931411111","username":"SadBoi","nickname":"SadBoi","serverId":1003,"worldId":1,"x":388,"y":636,"pointId":325827,"pointType":1,"level":66,"power":9277154,"armyPower":"392,511,577,641,404,400,000,000","armyPowerText":"393cc","allianceId":"100218933","allianceTag":"h3R0","allianceName":"Order of Heros","allianceRole":1,"rank":1,"isOnline":0,"joinTime":1776272216,"lastShowTime":1783783459,"lastLogin":1783783459,"language":"en","nationalflag":233,"gender":0,"usergender":1,"headFrameId":4,"source":{"map":true,"allianceMember":true},"powerRankInAlliance":19,"powerPercentileInAlliance":0.95,"powerContributionRate":0.011102,"cumulativePowerContributionRate":0.992536,"activityScore":70,"activityReasons":["map_found","recent_login_1d","high_role","alliance_member_confirmed"],"activityGrade":"ACTIVE","userStatus":"ACTIVE","inactiveScore":0,"inactiveReasons":["lastLoginWithin1Day"],"lastLoginDaysAgo":0.4},{"uid":"401136272656","username":"Chad","serverId":1003,"worldId":1003,"x":351,"y":637,"pointId":326320,"pointType":1,"level":80,"power":8228371,"armyPower":"11,043,889,924,730,180,000,000,000,000","armyPowerText":"11ee","allianceId":"200166734","allianceTag":"rdy?","language":"en","nationalflag":233,"gender":0,"usergender":1,"source":{"map":true},"powerRankInAlliance":1,"powerPercentileInAlliance":1,"powerContributionRate":1,"cumulativePowerContributionRate":1,"activityScore":30,"activityReasons":["map_found"],"activityGrade":"WATCH","userStatus":"UNKNOWN","inactiveScore":0,"inactiveReasons":["lastLogin_unknown"],"lastLoginDaysAgo":null},{"uid":"392696055001","username":"fernando","nickname":"fernando","serverId":1003,"worldId":1,"x":391,"y":639,"pointId":327364,"pointType":1,"level":63,"power":6236959,"armyPower":"76,776,268,914,847,940,000,000","armyPowerText":"76.8cc","allianceId":"100218933","allianceTag":"h3R0","allianceName":"Order of Heros","allianceRole":3,"rank":3,"isOnline":0,"joinTime":1781959609,"lastShowTime":1783806047,"lastLogin":1783806047,"language":"en","nationalflag":233,"gender":0,"usergender":1,"headFrameId":1,"source":{"map":true,"allianceMember":true},"powerRankInAlliance":20,"powerPercentileInAlliance":1,"powerContributionRate":0.007464,"cumulativePowerContributionRate":1,"activityScore":70,"activityReasons":["map_found","recent_login_1d","high_role","alliance_member_confirmed"],"activityGrade":"ACTIVE","userStatus":"ACTIVE","inactiveScore":0,"inactiveReasons":["lastLoginWithin1Day"],"lastLoginDaysAgo":0.14},{"uid":"399889675494","username":"azzoz","serverId":1003,"worldId":1003,"x":224,"y":718,"pointId":367729,"pointType":1,"level":49,"power":3003365,"armyPower":"2,831,037,150,371,276,300","armyPowerText":"2.83bb","allianceId":"200156457","allianceTag":"3jrm","language":"en","nationalflag":113,"gender":0,"usergender":1,"source":{"map":true},"powerRankInAlliance":1,"powerPercentileInAlliance":1,"powerContributionRate":1,"cumulativePowerContributionRate":1,"activityScore":30,"activityReasons":["map_found"],"activityGrade":"WATCH","userStatus":"UNKNOWN","inactiveScore":0,"inactiveReasons":["lastLogin_unknown"],"lastLoginDaysAgo":null},{"uid":"382081635443","username":"wy.382081635443","serverId":1003,"worldId":1003,"x":19,"y":349,"pointId":178698,"pointType":1,"level":53,"power":2295100,"armyPower":"6,690,253,254,600,574,000","armyPowerText":"6.69bb","allianceId":"100216214","allianceTag":"Spah","language":"en","nationalflag":233,"gender":0,"usergender":0,"source":{"map":true},"powerRankInAlliance":1,"powerPercentileInAlliance":1,"powerContributionRate":1,"cumulativePowerContributionRate":1,"activityScore":30,"activityReasons":["map_found"],"activityGrade":"WATCH","userStatus":"UNKNOWN","inactiveScore":0,"inactiveReasons":["lastLogin_unknown"],"lastLoginDaysAgo":null},{"uid":"382163104883","username":"忒有钱","serverId":1003,"worldId":1003,"x":680,"y":874,"pointId":447829,"pointType":1,"level":55,"power":2000495,"armyPower":"25,208,832,676,438,032,000","armyPowerText":"25.2bb","allianceId":"100216104","allianceTag":"ZHCN","language":"zh_cn","nationalflag":48,"gender":0,"usergender":0,"source":{"map":true},"powerRankInAlliance":1,"powerPercentileInAlliance":1,"powerContributionRate":1,"cumulativePowerContributionRate":1,"activityScore":30,"activityReasons":["map_found"],"activityGrade":"WATCH","userStatus":"UNKNOWN","inactiveScore":0,"inactiveReasons":["lastLogin_unknown"],"lastLoginDaysAgo":null},{"uid":"386458715306","username":"Linmar","serverId":1003,"worldId":1003,"x":572,"y":420,"pointId":215327,"pointType":1,"level":37,"power":1759220,"armyPower":"47,016,302,589,760","armyPowerText":"47T","language":"en","nationalflag":233,"gender":0,"usergender":0,"source":{"map":true},"userStatus":"UNKNOWN","inactiveScore":0,"inactiveReasons":["lastLogin_unknown"],"lastLoginDaysAgo":null},{"uid":"382774736009","username":"Soul","serverId":1003,"worldId":1003,"x":527,"y":251,"pointId":128776,"pointType":1,"level":23,"power":469085,"armyPower":"801,503,699","armyPowerText":"802M","allianceId":"100223650","allianceTag":"$GH$","language":"en","nationalflag":233,"gender":0,"usergender":0,"source":{"map":true},"powerRankInAlliance":1,"powerPercentileInAlliance":0.5,"powerContributionRate":0.855706,"cumulativePowerContributionRate":0.855706,"activityScore":45,"activityReasons":["map_found","top_50_power"],"activityGrade":"WATCH","userStatus":"UNKNOWN","inactiveScore":0,"inactiveReasons":["lastLogin_unknown"],"lastLoginDaysAgo":null},{"uid":"373197239336","username":"Broskii","serverId":1003,"worldId":1003,"x":118,"y":876,"pointId":448572,"pointType":1,"level":26,"power":336465,"armyPower":"2,691,851,807","armyPowerText":"2.69B","language":"en","nationalflag":233,"gender":0,"usergender":0,"source":{"map":true},"userStatus":"UNKNOWN","inactiveScore":0,"inactiveReasons":["lastLogin_unknown"],"lastLoginDaysAgo":null},{"uid":"386055324841","username":"wy.386055324841","serverId":1003,"worldId":1003,"x":91,"y":299,"pointId":153134,"pointType":1,"level":16,"power":79100,"armyPower":"11,285","armyPowerText":"11.3K","allianceId":"100223650","allianceTag":"$GH$","language":"en","nationalflag":233,"gender":0,"usergender":0,"source":{"map":true},"powerRankInAlliance":2,"powerPercentileInAlliance":1,"powerContributionRate":0.144294,"cumulativePowerContributionRate":1,"activityScore":30,"activityReasons":["map_found"],"activityGrade":"WATCH","userStatus":"UNKNOWN","inactiveScore":0,"inactiveReasons":["lastLogin_unknown"],"lastLoginDaysAgo":null}],"alliances":[{"memberCount":20,"allianceId":"100218933","allianceTag":"h3R0","allianceCode":"h3R0","allianceName":"Order of Heros","allianceLeader":"أبومروان","allianceLevel":5,"alliancePower":4240000000,"alliancePowerText":"4.24B","allianceMemberCountShown":150,"allianceMemberMax":170,"allianceMemberText":"150/170","serverId":1003,"activitySummary":{"collectedMapMemberCount":20,"coreCount":11,"activeCount":9,"watchCount":0,"lowCount":0,"activeTotalCount":20,"totalPower":835646779,"corePowerSum":632084289,"activePowerSum":835646779,"corePowerRate":0.756401,"activePowerRate":1,"top20PowerCount":4,"cumulative80PowerCount":11,"shownMemberCount":150,"shownMemberMax":170},"activeAllianceGrade":"WATCH","activeAllianceScore":66,"activeAllianceReasons":["coverageRate=13.33%","coverageRate<20%, grade capped to WATCH","coreCount>=10","activeCount>=5","memberCount>=10","powerRate_ignored_due_to_low_coverage"],"coverageRate":0.1333},{"memberCount":5,"allianceId":"100216886","allianceTag":"UDs1","allianceCode":"UDs1","allianceName":"Underdogs 1","allianceLeader":"RedWolf","allianceLevel":5,"alliancePower":2570000000,"alliancePowerText":"2.57B","allianceMemberCountShown":160,"allianceMemberMax":170,"allianceMemberText":"160/170","serverId":1003,"activitySummary":{"collectedMapMemberCount":5,"coreCount":4,"activeCount":1,"watchCount":0,"lowCount":0,"activeTotalCount":5,"totalPower":203661172,"corePowerSum":182603830,"activePowerSum":203661172,"corePowerRate":0.896606,"activePowerRate":1,"top20PowerCount":1,"cumulative80PowerCount":3,"shownMemberCount":160,"shownMemberMax":170},"activeAllianceGrade":"INSUFFICIENT","activeAllianceScore":0,"activeAllianceReasons":["coverageRate=3.13%","coverageRate<10%","sample_too_small_for_alliance_grade"],"coverageRate":0.0313},{"memberCount":4,"allianceId":"100215856","allianceTag":"RaVa","allianceCode":"RaVa","allianceName":"RAVAGERS","allianceLeader":"EZAir","allianceLevel":5,"alliancePower":2000000000,"alliancePowerText":"2B","allianceMemberCountShown":110,"allianceMemberMax":170,"allianceMemberText":"110/170","serverId":1003,"activitySummary":{"collectedMapMemberCount":4,"coreCount":2,"activeCount":1,"watchCount":1,"lowCount":0,"activeTotalCount":3,"totalPower":178278573,"corePowerSum":121091911,"activePowerSum":148977263,"corePowerRate":0.679229,"activePowerRate":0.835643,"top20PowerCount":0,"cumulative80PowerCount":2,"shownMemberCount":110,"shownMemberMax":170},"activeAllianceGrade":"INSUFFICIENT","activeAllianceScore":0,"activeAllianceReasons":["coverageRate=3.64%","coverageRate<10%","sample_too_small_for_alliance_grade"],"coverageRate":0.0364},{"memberCount":2,"allianceId":"100223650","allianceTag":"$GH$","serverId":1003,"activitySummary":{"collectedMapMemberCount":2,"coreCount":0,"activeCount":0,"watchCount":2,"lowCount":0,"activeTotalCount":0,"totalPower":548185,"corePowerSum":0,"activePowerSum":0,"corePowerRate":0,"activePowerRate":0,"top20PowerCount":0,"cumulative80PowerCount":0,"shownMemberCount":null,"shownMemberMax":null},"activeAllianceGrade":"LOW","activeAllianceScore":0,"activeAllianceReasons":["coverageRate=100%"],"coverageRate":1},{"memberCount":1,"allianceId":"100181606","allianceTag":"WECU","allianceCode":"WECU","allianceName":"Band of Misfit","allianceLeader":"Camokid","allianceLevel":5,"alliancePower":358000000,"alliancePowerText":"358M","allianceMemberCountShown":21,"allianceMemberMax":170,"allianceMemberText":"21/170","serverId":1003,"activitySummary":{"collectedMapMemberCount":1,"coreCount":0,"activeCount":1,"watchCount":0,"lowCount":0,"activeTotalCount":1,"totalPower":42474499,"corePowerSum":0,"activePowerSum":42474499,"corePowerRate":0,"activePowerRate":1,"top20PowerCount":0,"cumulative80PowerCount":0,"shownMemberCount":21,"shownMemberMax":170},"activeAllianceGrade":"LOW","activeAllianceScore":0,"activeAllianceReasons":["coverageRate=4.76%","powerRate_ignored_due_to_low_coverage"],"coverageRate":0.0476},{"memberCount":1,"allianceId":"100198341","allianceTag":"WR1$","serverId":1003,"activitySummary":{"collectedMapMemberCount":1,"coreCount":0,"activeCount":0,"watchCount":1,"lowCount":0,"activeTotalCount":0,"totalPower":23337375,"corePowerSum":0,"activePowerSum":0,"corePowerRate":0,"activePowerRate":0,"top20PowerCount":0,"cumulative80PowerCount":0,"shownMemberCount":null,"shownMemberMax":null},"activeAllianceGrade":"LOW","activeAllianceScore":0,"activeAllianceReasons":["coverageRate=100%"],"coverageRate":1},{"memberCount":1,"allianceId":"100214794","allianceTag":"GWRP","serverId":1003,"activitySummary":{"collectedMapMemberCount":1,"coreCount":0,"activeCount":0,"watchCount":1,"lowCount":0,"activeTotalCount":0,"totalPower":23409911,"corePowerSum":0,"activePowerSum":0,"corePowerRate":0,"activePowerRate":0,"top20PowerCount":0,"cumulative80PowerCount":0,"shownMemberCount":null,"shownMemberMax":null},"activeAllianceGrade":"LOW","activeAllianceScore":0,"activeAllianceReasons":["coverageRate=100%"],"coverageRate":1},{"memberCount":1,"allianceId":"100215290","allianceTag":"krj1","serverId":1003,"activitySummary":{"collectedMapMemberCount":1,"coreCount":0,"activeCount":0,"watchCount":1,"lowCount":0,"activeTotalCount":0,"totalPower":16065769,"corePowerSum":0,"activePowerSum":0,"corePowerRate":0,"activePowerRate":0,"top20PowerCount":0,"cumulative80PowerCount":0,"shownMemberCount":null,"shownMemberMax":null},"activeAllianceGrade":"LOW","activeAllianceScore":0,"activeAllianceReasons":["coverageRate=100%"],"coverageRate":1},{"memberCount":1,"allianceId":"100216104","allianceTag":"ZHCN","serverId":1003,"activitySummary":{"collectedMapMemberCount":1,"coreCount":0,"activeCount":0,"watchCount":1,"lowCount":0,"activeTotalCount":0,"totalPower":2000495,"corePowerSum":0,"activePowerSum":0,"corePowerRate":0,"activePowerRate":0,"top20PowerCount":0,"cumulative80PowerCount":0,"shownMemberCount":null,"shownMemberMax":null},"activeAllianceGrade":"LOW","activeAllianceScore":0,"activeAllianceReasons":["coverageRate=100%"],"coverageRate":1},{"memberCount":1,"allianceId":"100216214","allianceTag":"Spah","serverId":1003,"activitySummary":{"collectedMapMemberCount":1,"coreCount":0,"activeCount":0,"watchCount":1,"lowCount":0,"activeTotalCount":0,"totalPower":2295100,"corePowerSum":0,"activePowerSum":0,"corePowerRate":0,"activePowerRate":0,"top20PowerCount":0,"cumulative80PowerCount":0,"shownMemberCount":null,"shownMemberMax":null},"activeAllianceGrade":"LOW","activeAllianceScore":0,"activeAllianceReasons":["coverageRate=100%"],"coverageRate":1},{"memberCount":1,"allianceId":"100234927","allianceTag":"]CW[","serverId":1003,"activitySummary":{"collectedMapMemberCount":1,"coreCount":0,"activeCount":0,"watchCount":1,"lowCount":0,"activeTotalCount":0,"totalPower":26525829,"corePowerSum":0,"activePowerSum":0,"corePowerRate":0,"activePowerRate":0,"top20PowerCount":0,"cumulative80PowerCount":0,"shownMemberCount":null,"shownMemberMax":null},"activeAllianceGrade":"LOW","activeAllianceScore":0,"activeAllianceReasons":["coverageRate=100%"],"coverageRate":1},{"memberCount":1,"allianceId":"100237028","allianceTag":"WAL!","serverId":1003,"activitySummary":{"collectedMapMemberCount":1,"coreCount":0,"activeCount":0,"watchCount":1,"lowCount":0,"activeTotalCount":0,"totalPower":42419263,"corePowerSum":0,"activePowerSum":0,"corePowerRate":0,"activePowerRate":0,"top20PowerCount":0,"cumulative80PowerCount":0,"shownMemberCount":null,"shownMemberMax":null},"activeAllianceGrade":"LOW","activeAllianceScore":0,"activeAllianceReasons":["coverageRate=100%"],"coverageRate":1},{"memberCount":1,"allianceId":"100251205","allianceTag":"~JZb","serverId":1003,"activitySummary":{"collectedMapMemberCount":1,"coreCount":0,"activeCount":0,"watchCount":1,"lowCount":0,"activeTotalCount":0,"totalPower":18885510,"corePowerSum":0,"activePowerSum":0,"corePowerRate":0,"activePowerRate":0,"top20PowerCount":0,"cumulative80PowerCount":0,"shownMemberCount":null,"shownMemberMax":null},"activeAllianceGrade":"LOW","activeAllianceScore":0,"activeAllianceReasons":["coverageRate=100%"],"coverageRate":1},{"memberCount":1,"allianceId":"200156457","allianceTag":"3jrm","serverId":1003,"activitySummary":{"collectedMapMemberCount":1,"coreCount":0,"activeCount":0,"watchCount":1,"lowCount":0,"activeTotalCount":0,"totalPower":3003365,"corePowerSum":0,"activePowerSum":0,"corePowerRate":0,"activePowerRate":0,"top20PowerCount":0,"cumulative80PowerCount":0,"shownMemberCount":null,"shownMemberMax":null},"activeAllianceGrade":"LOW","activeAllianceScore":0,"activeAllianceReasons":["coverageRate=100%"],"coverageRate":1},{"memberCount":1,"allianceId":"200166734","allianceTag":"rdy?","serverId":1003,"activitySummary":{"collectedMapMemberCount":1,"coreCount":0,"activeCount":0,"watchCount":1,"lowCount":0,"activeTotalCount":0,"totalPower":8228371,"corePowerSum":0,"activePowerSum":0,"corePowerRate":0,"activePowerRate":0,"top20PowerCount":0,"cumulative80PowerCount":0,"shownMemberCount":null,"shownMemberMax":null},"activeAllianceGrade":"LOW","activeAllianceScore":0,"activeAllianceReasons":["coverageRate=100%"],"coverageRate":1},{"memberCount":1,"allianceId":"300101839","allianceTag":"edg2","serverId":1003,"activitySummary":{"collectedMapMemberCount":1,"coreCount":0,"activeCount":0,"watchCount":1,"lowCount":0,"activeTotalCount":0,"totalPower":33980342,"corePowerSum":0,"activePowerSum":0,"corePowerRate":0,"activePowerRate":0,"top20PowerCount":0,"cumulative80PowerCount":0,"shownMemberCount":null,"shownMemberMax":null},"activeAllianceGrade":"LOW","activeAllianceScore":0,"activeAllianceReasons":["coverageRate=100%"],"coverageRate":1},{"memberCount":1,"allianceId":"300109845","allianceTag":"|qCg","allianceCode":"|qCg","allianceName":"WYG3822","allianceLeader":"wy.382263293043","allianceLevel":0,"alliancePower":44500000,"alliancePowerText":"44.5M","allianceMemberCountShown":7,"allianceMemberMax":60,"allianceMemberText":"7/60","serverId":1003,"activitySummary":{"collectedMapMemberCount":1,"coreCount":0,"activeCount":1,"watchCount":0,"lowCount":0,"activeTotalCount":1,"totalPower":43466631,"corePowerSum":0,"activePowerSum":43466631,"corePowerRate":0,"activePowerRate":1,"top20PowerCount":0,"cumulative80PowerCount":0,"shownMemberCount":7,"shownMemberMax":60},"activeAllianceGrade":"LOW","activeAllianceScore":0,"activeAllianceReasons":["coverageRate=14.29%","powerRate_ignored_due_to_low_coverage"],"coverageRate":0.1429}]}