{"exportedAt":"2026-06-13T19:44:20.971Z","serverId":4077,"summary":{"players":89,"mapPlayers":89,"allianceMemberMergedPlayers":75,"mapOnlyPlayers":14,"noAlliancePlayers":4,"alliances":14,"allianceDetails":5,"activity":{"coreCount":44,"activeCount":32,"watchCount":9,"lowCount":0,"activeTotalCount":76},"allianceActivitySummary":{"coreAllianceCount":1,"activeAllianceCount":0,"watchAllianceCount":0,"lowAllianceCount":10,"insufficientAllianceCount":3,"activeAllianceCountForWar":1,"meaningfulAllianceCount":1},"serverActivity":{"grade":"NORMAL","score":43,"reasons":["coreAllianceCount>=1","activeAllianceCountForWar>=1","activeUsers>=40","corePlusActiveGradeUsers>=40","activeUserRate>=40%","activePowerRate>=65%","power_concentrated_top1_alliance","power_concentrated_top3_alliances"]},"serverActivitySummary":{"serverActivityGrade":"NORMAL","serverActivityScore":43,"serverActivityReasons":["coreAllianceCount>=1","activeAllianceCountForWar>=1","activeUsers>=40","corePlusActiveGradeUsers>=40","activeUserRate>=40%","activePowerRate>=65%","power_concentrated_top1_alliance","power_concentrated_top3_alliances"],"totalMapPlayers":89,"coreUsers":44,"activeGradeUsers":32,"watchGradeUsers":9,"lowGradeUsers":0,"activeUsers":75,"recentUsers":5,"sleepyUsers":6,"inactiveUsers":0,"quitLikelyUsers":0,"unknownStatusUsers":14,"activeUserRate":0.842697,"quitLikelyRate":0,"activeAllianceCountForWar":1,"meaningfulAllianceCount":1,"coreAllianceCount":1,"activeAllianceCount":0,"watchAllianceCount":0,"lowAllianceCount":10,"insufficientAllianceCount":3,"serverPowerTotal":2055930405,"activePowerTotal":2012458262,"activePowerRate":0.978855,"topAlliancePowerRate":0.867852,"top3AlliancePowerRate":0.95774},"userStatus":{"activeUsers":75,"recentUsers":5,"sleepyUsers":6,"inactiveUsers":0,"quitLikelyUsers":0,"unknownStatusUsers":14,"activeUserRate":0.842697,"quitLikelyRate":0},"activeAllianceCountForWar":1,"meaningfulAllianceCount":1,"excluded":"objects, objectsByType, allianceRepresentatives, member-only players"},"activityCriteria":{"grade":{"CORE":"activityScore >= 80","ACTIVE":"activityScore >= 50","WATCH":"activityScore >= 30","LOW":"activityScore < 30"},"score":{"map_found":30,"online":30,"recent_login_1d":25,"recent_login_3d":20,"recent_login_7d":10,"top_20_power":30,"top_50_power":15,"cumulative_power_80":25,"high_role":10,"alliance_member_confirmed":5},"note":"최종 대상은 지도에서 발견된 유저만 포함합니다. 길드원 목록에만 있는 유저는 보강용이며 최종 players에는 포함하지 않습니다."},"serverActivityCriteria":{"serverGrade":{"VERY_ACTIVE":"serverActivityScore >= 80","ACTIVE":"serverActivityScore >= 60","NORMAL":"serverActivityScore >= 40","QUIET":"serverActivityScore >= 20","DEAD":"serverActivityScore < 20"},"userStatus":{"ACTIVE":"online or lastLogin <= 1 day","RECENT":"lastLogin <= 3 days","SLEEPY":"lastLogin <= 7 days","INACTIVE":"lastLogin > 7 days or > 14 days","QUIT_LIKELY":"lastLogin > 30 days or > 14 days and not allianceMember confirmed","UNKNOWN":"lastLogin missing"}},"players":[{"uid":"9034998812653","username":"ろうひ","nickname":"ろうひ","serverId":4077,"worldId":1,"x":420,"y":640,"pointId":327891,"pointType":1,"level":100,"power":62778308,"armyPower":"2,141,255,539,622,775,700,000,000,000,000,000,000","armyPowerText":"2.14hh","allianceId":"500394827","allianceTag":"4o77","allianceName":"ぼんじーり","allianceRole":4,"rank":4,"isOnline":0,"joinTime":1746264558,"lastShowTime":1781363340,"lastLogin":1781363340,"language":"ja","nationalflag":114,"gender":0,"usergender":2,"headFrameId":0,"source":{"map":true,"allianceMember":true},"powerRankInAlliance":1,"powerPercentileInAlliance":0.0167,"powerContributionRate":0.035185,"cumulativePowerContributionRate":0.035185,"activityScore":125,"activityReasons":["map_found","top_20_power","cumulative_power_80","recent_login_1d","high_role","alliance_member_confirmed"],"activityGrade":"CORE","userStatus":"ACTIVE","inactiveScore":0,"inactiveReasons":["lastLoginWithin1Day"],"lastLoginDaysAgo":0.19},{"uid":"9068197154820","username":"DS_Lite","nickname":"DS_Lite","serverId":4077,"worldId":1,"x":427,"y":627,"pointId":321238,"pointType":1,"level":100,"power":51169839,"armyPower":"2,300,208,272,911,968,300,000,000,000,000,000,000","armyPowerText":"2.3hh","allianceId":"500394827","allianceTag":"4o77","allianceName":"ぼんじーり","allianceRole":3,"rank":3,"isOnline":1,"joinTime":1769350984,"lastShowTime":1781344331,"lastLogin":1781344331,"language":"ja","nationalflag":114,"gender":0,"usergender":1,"headFrameId":1,"source":{"map":true,"allianceMember":true},"powerRankInAlliance":2,"powerPercentileInAlliance":0.0333,"powerContributionRate":0.028679,"cumulativePowerContributionRate":0.063864,"activityScore":155,"activityReasons":["map_found","top_20_power","cumulative_power_80","online","recent_login_1d","high_role","alliance_member_confirmed"],"activityGrade":"CORE","userStatus":"ACTIVE","inactiveScore":0,"inactiveReasons":["online"],"lastLoginDaysAgo":0},{"uid":"9045037912045","username":"せさみん","nickname":"せさみん","serverId":4077,"worldId":1,"x":429,"y":625,"pointId":320215,"pointType":1,"level":100,"power":50317177,"armyPower":"2,346,729,565,301,924,600,000,000,000,000,000,000","armyPowerText":"2.35hh","allianceId":"500394827","allianceTag":"4o77","allianceName":"ぼんじーり","allianceRole":7,"rank":7,"isOnline":0,"joinTime":1750901295,"lastShowTime":1781361240,"lastLogin":1781361240,"language":"ja","nationalflag":114,"gender":0,"usergender":2,"headFrameId":0,"source":{"map":true,"allianceMember":true},"powerRankInAlliance":3,"powerPercentileInAlliance":0.05,"powerContributionRate":0.028201,"cumulativePowerContributionRate":0.092064,"activityScore":115,"activityReasons":["map_found","top_20_power","cumulative_power_80","recent_login_1d","alliance_member_confirmed"],"activityGrade":"CORE","userStatus":"ACTIVE","inactiveScore":0,"inactiveReasons":["lastLoginWithin1Day"],"lastLoginDaysAgo":0.22},{"uid":"9064004882432","username":"powantwo","nickname":"powantwo","serverId":4077,"worldId":1,"x":433,"y":629,"pointId":322265,"pointType":1,"level":100,"power":48327867,"armyPower":"1,755,034,899,516,545,000,000,000,000,000,000,000","armyPowerText":"1.76hh","allianceId":"500394827","allianceTag":"4o77","allianceName":"ぼんじーり","allianceRole":8,"rank":8,"isOnline":0,"joinTime":1767532894,"lastShowTime":1781354475,"lastLogin":1781354475,"language":"ja","nationalflag":114,"gender":0,"usergender":0,"headFrameId":151,"source":{"map":true,"allianceMember":true},"powerRankInAlliance":4,"powerPercentileInAlliance":0.0667,"powerContributionRate":0.027086,"cumulativePowerContributionRate":0.11915,"activityScore":115,"activityReasons":["map_found","top_20_power","cumulative_power_80","recent_login_1d","alliance_member_confirmed"],"activityGrade":"CORE","userStatus":"ACTIVE","inactiveScore":0,"inactiveReasons":["lastLoginWithin1Day"],"lastLoginDaysAgo":0.29},{"uid":"9060247015405","username":"ネス湖のてっぺん","nickname":"ネス湖のてっぺん","serverId":4077,"worldId":1,"x":433,"y":637,"pointId":326361,"pointType":1,"level":100,"power":47147578,"armyPower":"142,131,429,125,021,120,000,000,000,000,000,000","armyPowerText":"142gg","allianceId":"500394827","allianceTag":"4o77","allianceName":"ぼんじーり","allianceRole":6,"rank":6,"isOnline":0,"joinTime":1750861002,"lastShowTime":1781368481,"lastLogin":1781368481,"language":"ja","nationalflag":203,"gender":0,"usergender":1,"headFrameId":0,"source":{"map":true,"allianceMember":true},"powerRankInAlliance":5,"powerPercentileInAlliance":0.0833,"powerContributionRate":0.026424,"cumulativePowerContributionRate":0.145575,"activityScore":115,"activityReasons":["map_found","top_20_power","cumulative_power_80","recent_login_1d","alliance_member_confirmed"],"activityGrade":"CORE","userStatus":"ACTIVE","inactiveScore":0,"inactiveReasons":["lastLoginWithin1Day"],"lastLoginDaysAgo":0.13},{"uid":"9048222240749","username":"happy","nickname":"happy","serverId":4077,"worldId":1,"x":417,"y":633,"pointId":324305,"pointType":1,"level":100,"power":46905042,"armyPower":"1,385,823,199,353,774,600,000,000,000,000,000,000","armyPowerText":"1.39hh","allianceId":"500394827","allianceTag":"4o77","allianceName":"ぼんじーり","allianceRole":3,"rank":3,"isOnline":0,"joinTime":1748251805,"lastShowTime":1781377838,"lastLogin":1781377838,"language":"gk","nationalflag":122,"gender":0,"usergender":0,"headFrameId":157,"source":{"map":true,"allianceMember":true},"powerRankInAlliance":6,"powerPercentileInAlliance":0.1,"powerContributionRate":0.026288,"cumulativePowerContributionRate":0.171863,"activityScore":125,"activityReasons":["map_found","top_20_power","cumulative_power_80","recent_login_1d","high_role","alliance_member_confirmed"],"activityGrade":"CORE","userStatus":"ACTIVE","inactiveScore":0,"inactiveReasons":["lastLoginWithin1Day"],"lastLoginDaysAgo":0.02},{"uid":"9064767885316","username":"怠天使ダラケル","nickname":"怠天使ダラケル","serverId":4077,"worldId":1,"x":422,"y":642,"pointId":328916,"pointType":1,"level":100,"power":46690230,"armyPower":"144,891,817,915,017,440,000,000,000,000,000,000","armyPowerText":"145gg","allianceId":"500394827","allianceTag":"4o77","allianceName":"ぼんじーり","allianceRole":4,"rank":4,"isOnline":0,"joinTime":1769351487,"lastShowTime":1781370795,"lastLogin":1781370795,"language":"ja","nationalflag":114,"gender":0,"usergender":2,"headFrameId":159,"source":{"map":true,"allianceMember":true},"powerRankInAlliance":7,"powerPercentileInAlliance":0.1167,"powerContributionRate":0.026168,"cumulativePowerContributionRate":0.198031,"activityScore":125,"activityReasons":["map_found","top_20_power","cumulative_power_80","recent_login_1d","high_role","alliance_member_confirmed"],"activityGrade":"CORE","userStatus":"ACTIVE","inactiveScore":0,"inactiveReasons":["lastLoginWithin1Day"],"lastLoginDaysAgo":0.1},{"uid":"9066543124484","username":"tky","nickname":"tky","serverId":4077,"worldId":1,"x":425,"y":637,"pointId":326357,"pointType":1,"level":100,"power":44235330,"armyPower":"556,972,837,906,535,300,000,000,000,000,000,000","armyPowerText":"557gg","allianceId":"500394827","allianceTag":"4o77","allianceName":"ぼんじーり","allianceRole":3,"rank":3,"isOnline":0,"joinTime":1774877348,"lastShowTime":1781365339,"lastLogin":1781365339,"language":"ja","nationalflag":114,"gender":0,"usergender":0,"headFrameId":0,"source":{"map":true,"allianceMember":true},"powerRankInAlliance":8,"powerPercentileInAlliance":0.1333,"powerContributionRate":0.024792,"cumulativePowerContributionRate":0.222823,"activityScore":125,"activityReasons":["map_found","top_20_power","cumulative_power_80","recent_login_1d","high_role","alliance_member_confirmed"],"activityGrade":"CORE","userStatus":"ACTIVE","inactiveScore":0,"inactiveReasons":["lastLoginWithin1Day"],"lastLoginDaysAgo":0.17},{"uid":"9037354766317","username":"すえぞう","nickname":"すえぞう","serverId":4077,"worldId":1,"x":431,"y":631,"pointId":323288,"pointType":1,"level":100,"power":41775656,"armyPower":"1,115,772,836,822,198,000,000,000,000,000,000,000","armyPowerText":"1.12hh","allianceId":"500394827","allianceTag":"4o77","allianceName":"ぼんじーり","allianceRole":9,"rank":9,"isOnline":0,"joinTime":1750862451,"lastShowTime":1781363028,"lastLogin":1781363028,"language":"ja","nationalflag":114,"gender":0,"usergender":1,"headFrameId":159,"source":{"map":true,"allianceMember":true},"powerRankInAlliance":9,"powerPercentileInAlliance":0.15,"powerContributionRate":0.023414,"cumulativePowerContributionRate":0.246237,"activityScore":115,"activityReasons":["map_found","top_20_power","cumulative_power_80","recent_login_1d","alliance_member_confirmed"],"activityGrade":"CORE","userStatus":"ACTIVE","inactiveScore":0,"inactiveReasons":["lastLoginWithin1Day"],"lastLoginDaysAgo":0.19},{"uid":"9041364193261","username":"ドレミのフア🍫","nickname":"ドレミのフア🍫","serverId":4077,"worldId":1,"x":744,"y":246,"pointId":126325,"pointType":1,"level":100,"power":40312679,"armyPower":"1,431,176,095,962,017,700,000,000,000,000,000,000","armyPowerText":"1.43hh","allianceId":"500394827","allianceTag":"4o77","allianceName":"ぼんじーり","allianceRole":3,"rank":3,"isOnline":0,"joinTime":1768483654,"lastShowTime":1780927728,"lastLogin":1780927728,"language":"ja","nationalflag":114,"gender":0,"usergender":2,"headFrameId":108,"source":{"map":true,"allianceMember":true},"powerRankInAlliance":10,"powerPercentileInAlliance":0.1667,"powerContributionRate":0.022594,"cumulativePowerContributionRate":0.268831,"activityScore":110,"activityReasons":["map_found","top_20_power","cumulative_power_80","recent_login_7d","high_role","alliance_member_confirmed"],"activityGrade":"CORE","userStatus":"SLEEPY","inactiveScore":35,"inactiveReasons":["lastLoginWithin7Days"],"lastLoginDaysAgo":5.23},{"uid":"9052701396992","username":"アレクサ","nickname":"アレクサ","serverId":4077,"worldId":1,"x":423,"y":639,"pointId":327380,"pointType":1,"level":100,"power":40256830,"armyPower":"1,052,804,473,704,307,200,000,000,000,000,000,000","armyPowerText":"1.05hh","allianceId":"500394827","allianceTag":"4o77","allianceName":"ぼんじーり","allianceRole":4,"rank":4,"isOnline":0,"joinTime":1769951777,"lastShowTime":1781376303,"lastLogin":1781376303,"language":"ja","nationalflag":114,"gender":0,"usergender":1,"headFrameId":0,"source":{"map":true,"allianceMember":true},"powerRankInAlliance":11,"powerPercentileInAlliance":0.1833,"powerContributionRate":0.022562,"cumulativePowerContributionRate":0.291393,"activityScore":125,"activityReasons":["map_found","top_20_power","cumulative_power_80","recent_login_1d","high_role","alliance_member_confirmed"],"activityGrade":"CORE","userStatus":"ACTIVE","inactiveScore":0,"inactiveReasons":["lastLoginWithin1Day"],"lastLoginDaysAgo":0.04},{"uid":"9065169391620","username":"おうどん","nickname":"おうどん","serverId":4077,"worldId":1,"x":419,"y":635,"pointId":325330,"pointType":1,"level":100,"power":40014556,"armyPower":"80,380,705,817,147,550,000,000,000,000,000,000","armyPowerText":"80.4gg","allianceId":"500394827","allianceTag":"4o77","allianceName":"ぼんじーり","allianceRole":3,"rank":3,"isOnline":0,"joinTime":1771937102,"lastShowTime":1781365659,"lastLogin":1781365659,"language":"ja","nationalflag":114,"gender":0,"usergender":0,"headFrameId":8,"source":{"map":true,"allianceMember":true},"powerRankInAlliance":12,"powerPercentileInAlliance":0.2,"powerContributionRate":0.022427,"cumulativePowerContributionRate":0.31382,"activityScore":125,"activityReasons":["map_found","top_20_power","cumulative_power_80","recent_login_1d","high_role","alliance_member_confirmed"],"activityGrade":"CORE","userStatus":"ACTIVE","inactiveScore":0,"inactiveReasons":["lastLoginWithin1Day"],"lastLoginDaysAgo":0.16},{"uid":"9066020409348","username":"ポト","nickname":"ポト","serverId":4077,"worldId":1,"x":425,"y":625,"pointId":320213,"pointType":1,"level":100,"power":39975483,"armyPower":"796,615,830,335,551,000,000,000,000,000,000,000","armyPowerText":"797gg","allianceId":"500394827","allianceTag":"4o77","allianceName":"ぼんじーり","allianceRole":3,"rank":3,"isOnline":0,"joinTime":1769347552,"lastShowTime":1781358515,"lastLogin":1781358515,"language":"ja","nationalflag":114,"gender":0,"usergender":1,"headFrameId":157,"source":{"map":true,"allianceMember":true},"powerRankInAlliance":13,"powerPercentileInAlliance":0.2167,"powerContributionRate":0.022405,"cumulativePowerContributionRate":0.336225,"activityScore":110,"activityReasons":["map_found","top_50_power","cumulative_power_80","recent_login_1d","high_role","alliance_member_confirmed"],"activityGrade":"CORE","userStatus":"ACTIVE","inactiveScore":0,"inactiveReasons":["lastLoginWithin1Day"],"lastLoginDaysAgo":0.25},{"uid":"9046891466733","username":"等間隔","nickname":"等間隔","serverId":4077,"worldId":1,"x":435,"y":639,"pointId":327386,"pointType":1,"level":100,"power":39496214,"armyPower":"290,018,644,961,103,400,000,000,000,000,000,000","armyPowerText":"290gg","allianceId":"500394827","allianceTag":"4o77","allianceName":"ぼんじーり","allianceRole":3,"rank":3,"isOnline":0,"joinTime":1746611546,"lastShowTime":1781366852,"lastLogin":1781366852,"language":"ja","nationalflag":114,"gender":0,"usergender":0,"headFrameId":0,"source":{"map":true,"allianceMember":true},"powerRankInAlliance":14,"powerPercentileInAlliance":0.2333,"powerContributionRate":0.022136,"cumulativePowerContributionRate":0.358361,"activityScore":110,"activityReasons":["map_found","top_50_power","cumulative_power_80","recent_login_1d","high_role","alliance_member_confirmed"],"activityGrade":"CORE","userStatus":"ACTIVE","inactiveScore":0,"inactiveReasons":["lastLoginWithin1Day"],"lastLoginDaysAgo":0.15},{"uid":"9035718561773","username":"波羅蜜とねす","nickname":"波羅蜜とねす","serverId":4077,"worldId":1,"x":431,"y":619,"pointId":317144,"pointType":1,"level":100,"power":39453225,"armyPower":"193,767,294,376,910,840,000,000,000,000,000,000","armyPowerText":"194gg","allianceId":"500394827","allianceTag":"4o77","allianceName":"ぼんじーり","allianceRole":3,"rank":3,"isOnline":0,"joinTime":1750777390,"lastShowTime":1781379549,"lastLogin":1781379549,"language":"ja","nationalflag":101,"gender":0,"usergender":2,"headFrameId":0,"source":{"map":true,"allianceMember":true},"powerRankInAlliance":15,"powerPercentileInAlliance":0.25,"powerContributionRate":0.022112,"cumulativePowerContributionRate":0.380473,"activityScore":110,"activityReasons":["map_found","top_50_power","cumulative_power_80","recent_login_1d","high_role","alliance_member_confirmed"],"activityGrade":"CORE","userStatus":"ACTIVE","inactiveScore":0,"inactiveReasons":["lastLoginWithin1Day"],"lastLoginDaysAgo":0},{"uid":"9067386998788","username":"ozz","nickname":"ozz","serverId":4077,"worldId":1,"x":435,"y":619,"pointId":317146,"pointType":1,"level":100,"power":39270515,"armyPower":"55,721,379,436,907,230,000,000,000,000,000,000","armyPowerText":"55.7gg","allianceId":"500394827","allianceTag":"4o77","allianceName":"ぼんじーり","allianceRole":3,"rank":3,"isOnline":0,"joinTime":1774877559,"lastShowTime":1781369328,"lastLogin":1781369328,"language":"ja","nationalflag":114,"gender":0,"usergender":0,"headFrameId":0,"source":{"map":true,"allianceMember":true},"powerRankInAlliance":16,"powerPercentileInAlliance":0.2667,"powerContributionRate":0.02201,"cumulativePowerContributionRate":0.402482,"activityScore":110,"activityReasons":["map_found","top_50_power","cumulative_power_80","recent_login_1d","high_role","alliance_member_confirmed"],"activityGrade":"CORE","userStatus":"ACTIVE","inactiveScore":0,"inactiveReasons":["lastLoginWithin1Day"],"lastLoginDaysAgo":0.12},{"uid":"9035007987693","username":"KPz56","nickname":"KPz56","serverId":4077,"worldId":1,"x":429,"y":649,"pointId":332503,"pointType":1,"level":100,"power":38867874,"armyPower":"719,582,938,160,653,000,000,000,000,000,000,000","armyPowerText":"720gg","allianceId":"500394827","allianceTag":"4o77","allianceName":"ぼんじーり","allianceRole":3,"rank":3,"isOnline":0,"joinTime":1745838021,"lastShowTime":1781356151,"lastLogin":1781356151,"language":"ja","nationalflag":114,"gender":0,"usergender":1,"headFrameId":0,"source":{"map":true,"allianceMember":true},"powerRankInAlliance":17,"powerPercentileInAlliance":0.2833,"powerContributionRate":0.021784,"cumulativePowerContributionRate":0.424266,"activityScore":110,"activityReasons":["map_found","top_50_power","cumulative_power_80","recent_login_1d","high_role","alliance_member_confirmed"],"activityGrade":"CORE","userStatus":"ACTIVE","inactiveScore":0,"inactiveReasons":["lastLoginWithin1Day"],"lastLoginDaysAgo":0.27},{"uid":"9048442769408","username":"ฅナルナル♪","nickname":"ฅナルナル♪","serverId":4077,"worldId":1,"x":429,"y":637,"pointId":326359,"pointType":1,"level":100,"power":38566143,"armyPower":"1,407,330,333,643,925,000,000,000,000,000,000,000","armyPowerText":"1.41hh","allianceId":"500394827","allianceTag":"4o77","allianceName":"ぼんじーり","allianceRole":3,"rank":3,"isOnline":0,"joinTime":1767538734,"lastShowTime":1781365119,"lastLogin":1781365119,"language":"ja","nationalflag":114,"gender":0,"usergender":2,"headFrameId":0,"source":{"map":true,"allianceMember":true},"powerRankInAlliance":18,"powerPercentileInAlliance":0.3,"powerContributionRate":0.021615,"cumulativePowerContributionRate":0.445881,"activityScore":110,"activityReasons":["map_found","top_50_power","cumulative_power_80","recent_login_1d","high_role","alliance_member_confirmed"],"activityGrade":"CORE","userStatus":"ACTIVE","inactiveScore":0,"inactiveReasons":["lastLoginWithin1Day"],"lastLoginDaysAgo":0.17},{"uid":"9045112950765","username":"ダミア","nickname":"ダミア","serverId":4077,"worldId":1,"x":663,"y":271,"pointId":139084,"pointType":1,"level":100,"power":37011103,"armyPower":"488,986,578,908,095,060,000,000,000,000,000,000","armyPowerText":"489gg","allianceId":"500396289","allianceTag":"s5xA","allianceName":"グランteamA","allianceRole":6,"rank":6,"isOnline":0,"joinTime":1751102421,"lastShowTime":1781377604,"lastLogin":1781377604,"language":"ja","nationalflag":114,"gender":0,"usergender":0,"headFrameId":8,"source":{"map":true,"allianceMember":true},"powerRankInAlliance":1,"powerPercentileInAlliance":0.1111,"powerContributionRate":0.285435,"cumulativePowerContributionRate":0.285435,"activityScore":115,"activityReasons":["map_found","top_20_power","cumulative_power_80","recent_login_1d","alliance_member_confirmed"],"activityGrade":"CORE","userStatus":"ACTIVE","inactiveScore":0,"inactiveReasons":["lastLoginWithin1Day"],"lastLoginDaysAgo":0.03},{"uid":"9035947118573","username":"あかさ🍫🍨","nickname":"あかさ🍫🍨","serverId":4077,"worldId":1,"x":415,"y":635,"pointId":325328,"pointType":1,"level":100,"power":36645188,"armyPower":"1,056,559,115,114,734,900,000,000,000,000,000,000","armyPowerText":"1.06hh","allianceId":"500394827","allianceTag":"4o77","allianceName":"ぼんじーり","allianceRole":5,"rank":5,"isOnline":0,"joinTime":1745899910,"lastShowTime":1781361340,"lastLogin":1781361340,"language":"ja","nationalflag":114,"gender":0,"usergender":1,"headFrameId":159,"source":{"map":true,"allianceMember":true},"powerRankInAlliance":19,"powerPercentileInAlliance":0.3167,"powerContributionRate":0.020538,"cumulativePowerContributionRate":0.466419,"activityScore":100,"activityReasons":["map_found","top_50_power","cumulative_power_80","recent_login_1d","alliance_member_confirmed"],"activityGrade":"CORE","userStatus":"ACTIVE","inactiveScore":0,"inactiveReasons":["lastLoginWithin1Day"],"lastLoginDaysAgo":0.21},{"uid":"9064894074884","username":"みず","nickname":"みず","serverId":4077,"worldId":1,"x":433,"y":633,"pointId":324313,"pointType":1,"level":100,"power":35886098,"armyPower":"84,786,588,812,022,390,000,000,000,000,000,000","armyPowerText":"84.8gg","allianceId":"500394827","allianceTag":"4o77","allianceName":"ぼんじーり","allianceRole":3,"rank":3,"isOnline":0,"joinTime":1775866010,"lastShowTime":1781364433,"lastLogin":1781364433,"language":"ja","nationalflag":114,"gender":0,"usergender":1,"headFrameId":145,"source":{"map":true,"allianceMember":true},"powerRankInAlliance":20,"powerPercentileInAlliance":0.3333,"powerContributionRate":0.020113,"cumulativePowerContributionRate":0.486532,"activityScore":110,"activityReasons":["map_found","top_50_power","cumulative_power_80","recent_login_1d","high_role","alliance_member_confirmed"],"activityGrade":"CORE","userStatus":"ACTIVE","inactiveScore":0,"inactiveReasons":["lastLoginWithin1Day"],"lastLoginDaysAgo":0.18},{"uid":"9047076114413","username":"奏","nickname":"奏","serverId":4077,"worldId":1,"x":436,"y":634,"pointId":324827,"pointType":1,"level":100,"power":35647230,"armyPower":"1,424,082,399,877,322,000,000,000,000,000,000,000","armyPowerText":"1.42hh","allianceId":"500394827","allianceTag":"4o77","allianceName":"ぼんじーり","allianceRole":3,"rank":3,"isOnline":0,"joinTime":1748864861,"lastShowTime":1781354884,"lastLogin":1781354884,"language":"ja","nationalflag":114,"gender":0,"usergender":2,"headFrameId":133,"source":{"map":true,"allianceMember":true},"powerRankInAlliance":21,"powerPercentileInAlliance":0.35,"powerContributionRate":0.019979,"cumulativePowerContributionRate":0.506511,"activityScore":110,"activityReasons":["map_found","top_50_power","cumulative_power_80","recent_login_1d","high_role","alliance_member_confirmed"],"activityGrade":"CORE","userStatus":"ACTIVE","inactiveScore":0,"inactiveReasons":["lastLoginWithin1Day"],"lastLoginDaysAgo":0.29},{"uid":"9035281764333","username":"こむけい","nickname":"こむけい","serverId":4077,"worldId":1,"x":427,"y":611,"pointId":313046,"pointType":1,"level":100,"power":35539231,"armyPower":"1,239,978,828,001,280,600,000,000,000,000,000,000","armyPowerText":"1.24hh","allianceId":"500394827","allianceTag":"4o77","allianceName":"ぼんじーり","allianceRole":3,"rank":3,"isOnline":0,"joinTime":1745902134,"lastShowTime":1781360005,"lastLogin":1781360005,"language":"ja","nationalflag":114,"gender":0,"usergender":0,"headFrameId":157,"source":{"map":true,"allianceMember":true},"powerRankInAlliance":22,"powerPercentileInAlliance":0.3667,"powerContributionRate":0.019918,"cumulativePowerContributionRate":0.526429,"activityScore":110,"activityReasons":["map_found","top_50_power","cumulative_power_80","recent_login_1d","high_role","alliance_member_confirmed"],"activityGrade":"CORE","userStatus":"ACTIVE","inactiveScore":0,"inactiveReasons":["lastLoginWithin1Day"],"lastLoginDaysAgo":0.23},{"uid":"9036122886125","username":"ねこまる","nickname":"ねこまる","serverId":4077,"worldId":1,"x":436,"y":630,"pointId":322779,"pointType":1,"level":100,"power":35509550,"armyPower":"912,458,662,281,765,500,000,000,000,000,000,000","armyPowerText":"912gg","allianceId":"500394827","allianceTag":"4o77","allianceName":"ぼんじーり","allianceRole":3,"rank":3,"isOnline":0,"joinTime":1746182273,"lastShowTime":1781361952,"lastLogin":1781361952,"language":"ja","nationalflag":114,"gender":0,"usergender":2,"headFrameId":0,"source":{"map":true,"allianceMember":true},"powerRankInAlliance":23,"powerPercentileInAlliance":0.3833,"powerContributionRate":0.019902,"cumulativePowerContributionRate":0.546331,"activityScore":110,"activityReasons":["map_found","top_50_power","cumulative_power_80","recent_login_1d","high_role","alliance_member_confirmed"],"activityGrade":"CORE","userStatus":"ACTIVE","inactiveScore":0,"inactiveReasons":["lastLoginWithin1Day"],"lastLoginDaysAgo":0.21},{"uid":"9039708622829","username":"STEVEN","nickname":"STEVEN","serverId":4077,"worldId":1,"x":662,"y":260,"pointId":133452,"pointType":1,"level":100,"power":34349184,"armyPower":"444,054,949,912,438,000,000,000,000,000,000,000","armyPowerText":"444gg","allianceId":"500396289","allianceTag":"s5xA","allianceName":"グランteamA","allianceRole":4,"rank":4,"isOnline":0,"joinTime":1756286167,"lastShowTime":1781364081,"lastLogin":1781364081,"language":"gt","nationalflag":241,"gender":0,"usergender":0,"headFrameId":8,"source":{"map":true,"allianceMember":true},"powerRankInAlliance":2,"powerPercentileInAlliance":0.2222,"powerContributionRate":0.264906,"cumulativePowerContributionRate":0.550341,"activityScore":110,"activityReasons":["map_found","top_50_power","cumulative_power_80","recent_login_1d","high_role","alliance_member_confirmed"],"activityGrade":"CORE","userStatus":"ACTIVE","inactiveScore":0,"inactiveReasons":["lastLoginWithin1Day"],"lastLoginDaysAgo":0.18},{"uid":"9046851260397","username":"sas","nickname":"sas","serverId":4077,"worldId":1,"x":345,"y":457,"pointId":234157,"pointType":1,"level":100,"power":34065368,"armyPower":"171,367,968,138,784,150,000,000,000,000,000,000","armyPowerText":"171gg","allianceId":"500396177","allianceTag":"l__1","allianceName":"無言ポイ活a","allianceRole":5,"rank":5,"isOnline":0,"joinTime":1746508880,"lastShowTime":1781375420,"lastLogin":1781375420,"language":"ja","nationalflag":114,"gender":0,"usergender":0,"headFrameId":157,"source":{"map":true,"allianceMember":true},"powerRankInAlliance":1,"powerPercentileInAlliance":0.5,"powerContributionRate":0.617828,"cumulativePowerContributionRate":0.617828,"activityScore":100,"activityReasons":["map_found","top_50_power","cumulative_power_80","recent_login_1d","alliance_member_confirmed"],"activityGrade":"CORE","userStatus":"ACTIVE","inactiveScore":0,"inactiveReasons":["lastLoginWithin1Day"],"lastLoginDaysAgo":0.05},{"uid":"9141879672902","username":"えれめんとたわー","nickname":"えれめんとたわー","serverId":4077,"worldId":1,"x":438,"y":644,"pointId":329948,"pointType":1,"level":100,"power":33738953,"armyPower":"479,118,997,620,522,800,000,000,000,000,000,000","armyPowerText":"479gg","allianceId":"500394827","allianceTag":"4o77","allianceName":"ぼんじーり","allianceRole":4,"rank":4,"isOnline":0,"joinTime":1772400738,"lastShowTime":1781353620,"lastLogin":1781353620,"language":"ja","nationalflag":114,"gender":0,"usergender":1,"headFrameId":0,"source":{"map":true,"allianceMember":true},"powerRankInAlliance":24,"powerPercentileInAlliance":0.4,"powerContributionRate":0.018909,"cumulativePowerContributionRate":0.56524,"activityScore":110,"activityReasons":["map_found","top_50_power","cumulative_power_80","recent_login_1d","high_role","alliance_member_confirmed"],"activityGrade":"CORE","userStatus":"ACTIVE","inactiveScore":0,"inactiveReasons":["lastLoginWithin1Day"],"lastLoginDaysAgo":0.3},{"uid":"9036282007533","username":"もやし","nickname":"もやし","serverId":4077,"worldId":1,"x":418,"y":630,"pointId":322770,"pointType":1,"level":100,"power":33723895,"armyPower":"157,891,152,605,804,860,000,000,000,000,000,000","armyPowerText":"158gg","allianceId":"500394827","allianceTag":"4o77","allianceName":"ぼんじーり","allianceRole":3,"rank":3,"isOnline":0,"joinTime":1748791853,"lastShowTime":1781367216,"lastLogin":1781367216,"language":"ja","nationalflag":114,"gender":0,"usergender":1,"headFrameId":0,"source":{"map":true,"allianceMember":true},"powerRankInAlliance":25,"powerPercentileInAlliance":0.4167,"powerContributionRate":0.018901,"cumulativePowerContributionRate":0.584141,"activityScore":110,"activityReasons":["map_found","top_50_power","cumulative_power_80","recent_login_1d","high_role","alliance_member_confirmed"],"activityGrade":"CORE","userStatus":"ACTIVE","inactiveScore":0,"inactiveReasons":["lastLoginWithin1Day"],"lastLoginDaysAgo":0.15},{"uid":"9064996179972","username":"Kpz001","nickname":"Kpz001","serverId":4077,"worldId":1,"x":427,"y":643,"pointId":329430,"pointType":1,"level":100,"power":33517028,"armyPower":"100,801,765,711,661,660,000,000,000,000,000,000","armyPowerText":"101gg","allianceId":"500394827","allianceTag":"4o77","allianceName":"ぼんじーり","allianceRole":3,"rank":3,"isOnline":0,"joinTime":1776377681,"lastShowTime":1781367312,"lastLogin":1781367312,"language":"ja","nationalflag":114,"gender":0,"usergender":0,"headFrameId":0,"source":{"map":true,"allianceMember":true},"powerRankInAlliance":26,"powerPercentileInAlliance":0.4333,"powerContributionRate":0.018785,"cumulativePowerContributionRate":0.602926,"activityScore":110,"activityReasons":["map_found","top_50_power","cumulative_power_80","recent_login_1d","high_role","alliance_member_confirmed"],"activityGrade":"CORE","userStatus":"ACTIVE","inactiveScore":0,"inactiveReasons":["lastLoginWithin1Day"],"lastLoginDaysAgo":0.15},{"uid":"9037614354413","username":"yusuke02","nickname":"yusuke02","serverId":4077,"worldId":1,"x":412,"y":632,"pointId":323791,"pointType":1,"level":100,"power":33460300,"armyPower":"889,163,266,449,033,500,000,000,000,000,000,000","armyPowerText":"889gg","allianceId":"500394827","allianceTag":"4o77","allianceName":"ぼんじーり","allianceRole":3,"rank":3,"isOnline":1,"joinTime":1761883563,"lastShowTime":1781379499,"lastLogin":1781379499,"language":"ja","nationalflag":114,"gender":0,"usergender":0,"headFrameId":1,"source":{"map":true,"allianceMember":true},"powerRankInAlliance":27,"powerPercentileInAlliance":0.45,"powerContributionRate":0.018753,"cumulativePowerContributionRate":0.62168,"activityScore":140,"activityReasons":["map_found","top_50_power","cumulative_power_80","online","recent_login_1d","high_role","alliance_member_confirmed"],"activityGrade":"CORE","userStatus":"ACTIVE","inactiveScore":0,"inactiveReasons":["online"],"lastLoginDaysAgo":0},{"uid":"9061419814912","username":"カイト","nickname":"カイト","serverId":4077,"worldId":1,"x":424,"y":632,"pointId":323797,"pointType":1,"level":100,"power":32804956,"armyPower":"769,574,915,201,956,500,000,000,000,000,000,000","armyPowerText":"770gg","allianceId":"500394827","allianceTag":"4o77","allianceName":"ぼんじーり","allianceRole":3,"rank":3,"isOnline":0,"joinTime":1774254930,"lastShowTime":1781323463,"lastLogin":1781323463,"language":"ja","nationalflag":114,"gender":0,"usergender":2,"headFrameId":0,"source":{"map":true,"allianceMember":true},"powerRankInAlliance":28,"powerPercentileInAlliance":0.4667,"powerContributionRate":0.018386,"cumulativePowerContributionRate":0.640066,"activityScore":110,"activityReasons":["map_found","top_50_power","cumulative_power_80","recent_login_1d","high_role","alliance_member_confirmed"],"activityGrade":"CORE","userStatus":"ACTIVE","inactiveScore":0,"inactiveReasons":["lastLoginWithin1Day"],"lastLoginDaysAgo":0.65},{"uid":"9076729221124","username":"あるふぇ","nickname":"あるふぇ","serverId":4077,"worldId":1,"x":440,"y":636,"pointId":325853,"pointType":1,"level":100,"power":32804171,"armyPower":"852,513,633,799,794,400,000,000,000,000,000,000","armyPowerText":"853gg","allianceId":"500394827","allianceTag":"4o77","allianceName":"ぼんじーり","allianceRole":3,"rank":3,"isOnline":0,"joinTime":1771280722,"lastShowTime":1781360235,"lastLogin":1781360235,"language":"ja","nationalflag":218,"gender":0,"usergender":0,"headFrameId":0,"source":{"map":true,"allianceMember":true},"powerRankInAlliance":29,"powerPercentileInAlliance":0.4833,"powerContributionRate":0.018385,"cumulativePowerContributionRate":0.658451,"activityScore":110,"activityReasons":["map_found","top_50_power","cumulative_power_80","recent_login_1d","high_role","alliance_member_confirmed"],"activityGrade":"CORE","userStatus":"ACTIVE","inactiveScore":0,"inactiveReasons":["lastLoginWithin1Day"],"lastLoginDaysAgo":0.23},{"uid":"9072550318084","username":"トキノアルト","nickname":"トキノアルト","serverId":4077,"worldId":1,"x":421,"y":637,"pointId":326355,"pointType":1,"level":100,"power":32621506,"armyPower":"1,132,184,253,260,030,800,000,000,000,000,000,000","armyPowerText":"1.13hh","allianceId":"500394827","allianceTag":"4o77","allianceName":"ぼんじーり","allianceRole":3,"rank":3,"isOnline":0,"joinTime":1769344904,"lastShowTime":1781356567,"lastLogin":1781356567,"language":"ja","nationalflag":114,"gender":0,"usergender":0,"headFrameId":0,"source":{"map":true,"allianceMember":true},"powerRankInAlliance":30,"powerPercentileInAlliance":0.5,"powerContributionRate":0.018283,"cumulativePowerContributionRate":0.676734,"activityScore":110,"activityReasons":["map_found","top_50_power","cumulative_power_80","recent_login_1d","high_role","alliance_member_confirmed"],"activityGrade":"CORE","userStatus":"ACTIVE","inactiveScore":0,"inactiveReasons":["lastLoginWithin1Day"],"lastLoginDaysAgo":0.27},{"uid":"9035010445293","username":"ポチコフ🍫","nickname":"ポチコフ🍫","serverId":4077,"worldId":1,"x":433,"y":625,"pointId":320217,"pointType":1,"level":100,"power":32480245,"armyPower":"1","armyPowerText":"1","allianceId":"500394827","allianceTag":"4o77","allianceName":"ぼんじーり","allianceRole":3,"rank":3,"isOnline":0,"joinTime":1745898192,"lastShowTime":1781305706,"lastLogin":1781305706,"language":"ja","nationalflag":189,"gender":0,"usergender":2,"headFrameId":142,"source":{"map":true,"allianceMember":true},"powerRankInAlliance":31,"powerPercentileInAlliance":0.5167,"powerContributionRate":0.018204,"cumulativePowerContributionRate":0.694938,"activityScore":95,"activityReasons":["map_found","cumulative_power_80","recent_login_1d","high_role","alliance_member_confirmed"],"activityGrade":"CORE","userStatus":"ACTIVE","inactiveScore":0,"inactiveReasons":["lastLoginWithin1Day"],"lastLoginDaysAgo":0.86},{"uid":"9035549642733","username":"やらりん","nickname":"やらりん","serverId":4077,"worldId":1,"x":433,"y":645,"pointId":330457,"pointType":1,"level":100,"power":31609210,"armyPower":"593,440,871,413,562,900,000,000,000,000,000,000","armyPowerText":"593gg","allianceId":"500394827","allianceTag":"4o77","allianceName":"ぼんじーり","allianceRole":3,"rank":3,"isOnline":0,"joinTime":1745869648,"lastShowTime":1781365170,"lastLogin":1781365170,"language":"ja","nationalflag":114,"gender":0,"usergender":1,"headFrameId":13,"source":{"map":true,"allianceMember":true},"powerRankInAlliance":32,"powerPercentileInAlliance":0.5333,"powerContributionRate":0.017716,"cumulativePowerContributionRate":0.712654,"activityScore":95,"activityReasons":["map_found","cumulative_power_80","recent_login_1d","high_role","alliance_member_confirmed"],"activityGrade":"CORE","userStatus":"ACTIVE","inactiveScore":0,"inactiveReasons":["lastLoginWithin1Day"],"lastLoginDaysAgo":0.17},{"uid":"9040473395181","username":"花鳥風月☆","nickname":"花鳥風月☆","serverId":4077,"worldId":1,"x":429,"y":633,"pointId":324311,"pointType":1,"level":100,"power":30836007,"armyPower":"95,271,290,847,580,560,000,000,000,000,000,000","armyPowerText":"95.3gg","allianceId":"500394827","allianceTag":"4o77","allianceName":"ぼんじーり","allianceRole":3,"rank":3,"isOnline":0,"joinTime":1746708547,"lastShowTime":1781343982,"lastLogin":1781343982,"language":"ja","nationalflag":114,"gender":0,"usergender":0,"headFrameId":0,"source":{"map":true,"allianceMember":true},"powerRankInAlliance":33,"powerPercentileInAlliance":0.55,"powerContributionRate":0.017282,"cumulativePowerContributionRate":0.729936,"activityScore":95,"activityReasons":["map_found","cumulative_power_80","recent_login_1d","high_role","alliance_member_confirmed"],"activityGrade":"CORE","userStatus":"ACTIVE","inactiveScore":0,"inactiveReasons":["lastLoginWithin1Day"],"lastLoginDaysAgo":0.42},{"uid":"9054286221312","username":"あてぃし","nickname":"あてぃし","serverId":4077,"worldId":1,"x":425,"y":619,"pointId":317141,"pointType":1,"level":100,"power":30701075,"armyPower":"1,149,254,088,055,604,000,000,000,000,000,000,000","armyPowerText":"1.15hh","allianceId":"500394827","allianceTag":"4o77","allianceName":"ぼんじーり","allianceRole":3,"rank":3,"isOnline":0,"joinTime":1769960147,"lastShowTime":1781367578,"lastLogin":1781367578,"language":"ja","nationalflag":101,"gender":0,"usergender":2,"headFrameId":162,"source":{"map":true,"allianceMember":true},"powerRankInAlliance":34,"powerPercentileInAlliance":0.5667,"powerContributionRate":0.017207,"cumulativePowerContributionRate":0.747143,"activityScore":95,"activityReasons":["map_found","cumulative_power_80","recent_login_1d","high_role","alliance_member_confirmed"],"activityGrade":"CORE","userStatus":"ACTIVE","inactiveScore":0,"inactiveReasons":["lastLoginWithin1Day"],"lastLoginDaysAgo":0.14},{"uid":"9072393752580","username":"Calpeale","nickname":"Calpeale","serverId":4077,"worldId":1,"x":428,"y":640,"pointId":327895,"pointType":1,"level":100,"power":30397908,"armyPower":"908,857,981,013,307,700,000,000,000,000,000,000","armyPowerText":"909gg","allianceId":"500394827","allianceTag":"4o77","allianceName":"ぼんじーり","allianceRole":3,"rank":3,"isOnline":0,"joinTime":1775684348,"lastShowTime":1781371422,"lastLogin":1781371422,"language":"ja","nationalflag":114,"gender":0,"usergender":0,"headFrameId":0,"source":{"map":true,"allianceMember":true},"powerRankInAlliance":35,"powerPercentileInAlliance":0.5833,"powerContributionRate":0.017037,"cumulativePowerContributionRate":0.76418,"activityScore":95,"activityReasons":["map_found","cumulative_power_80","recent_login_1d","high_role","alliance_member_confirmed"],"activityGrade":"CORE","userStatus":"ACTIVE","inactiveScore":0,"inactiveReasons":["lastLoginWithin1Day"],"lastLoginDaysAgo":0.1},{"uid":"9046274412525","username":"ハゲタカ","nickname":"ハゲタカ","serverId":4077,"worldId":1,"x":429,"y":621,"pointId":318167,"pointType":1,"level":100,"power":30208611,"armyPower":"488,690,071,319,229,300,000,000,000,000,000,000","armyPowerText":"489gg","allianceId":"500394827","allianceTag":"4o77","allianceName":"ぼんじーり","allianceRole":3,"rank":3,"isOnline":1,"joinTime":1748352362,"lastShowTime":1781374973,"lastLogin":1781374973,"language":"ja","nationalflag":114,"gender":0,"usergender":0,"headFrameId":0,"source":{"map":true,"allianceMember":true},"powerRankInAlliance":36,"powerPercentileInAlliance":0.6,"powerContributionRate":0.016931,"cumulativePowerContributionRate":0.781111,"activityScore":125,"activityReasons":["map_found","cumulative_power_80","online","recent_login_1d","high_role","alliance_member_confirmed"],"activityGrade":"CORE","userStatus":"ACTIVE","inactiveScore":0,"inactiveReasons":["online"],"lastLoginDaysAgo":0},{"uid":"9043432443885","username":"Lopher","nickname":"Lopher","serverId":4077,"worldId":1,"x":423,"y":607,"pointId":310996,"pointType":1,"level":100,"power":29334324,"armyPower":"644,199,684,226,646,000,000,000,000,000,000,000","armyPowerText":"644gg","allianceId":"500394827","allianceTag":"4o77","allianceName":"ぼんじーり","allianceRole":3,"rank":3,"isOnline":0,"joinTime":1748872313,"lastShowTime":1781378284,"lastLogin":1781378284,"language":"ja","nationalflag":114,"gender":0,"usergender":0,"headFrameId":54,"source":{"map":true,"allianceMember":true},"powerRankInAlliance":37,"powerPercentileInAlliance":0.6167,"powerContributionRate":0.016441,"cumulativePowerContributionRate":0.797551,"activityScore":95,"activityReasons":["map_found","cumulative_power_80","recent_login_1d","high_role","alliance_member_confirmed"],"activityGrade":"CORE","userStatus":"ACTIVE","inactiveScore":0,"inactiveReasons":["lastLoginWithin1Day"],"lastLoginDaysAgo":0.02},{"uid":"9194488008793","username":"Roya","nickname":"Roya","serverId":4077,"worldId":1,"x":421,"y":621,"pointId":318163,"pointType":1,"level":100,"power":27750972,"armyPower":"1","armyPowerText":"1","allianceId":"500394827","allianceTag":"4o77","allianceName":"ぼんじーり","allianceRole":3,"rank":3,"isOnline":0,"joinTime":1776032419,"lastShowTime":1781353103,"lastLogin":1781353103,"language":"ja","nationalflag":114,"gender":0,"usergender":1,"headFrameId":126,"source":{"map":true,"allianceMember":true},"powerRankInAlliance":38,"powerPercentileInAlliance":0.6333,"powerContributionRate":0.015553,"cumulativePowerContributionRate":0.813105,"activityScore":70,"activityReasons":["map_found","recent_login_1d","high_role","alliance_member_confirmed"],"activityGrade":"ACTIVE","userStatus":"ACTIVE","inactiveScore":0,"inactiveReasons":["lastLoginWithin1Day"],"lastLoginDaysAgo":0.31},{"uid":"9043501551597","username":"まるはぴ","nickname":"まるはぴ","serverId":4077,"worldId":1,"x":431,"y":649,"pointId":332504,"pointType":1,"level":95,"power":27261991,"armyPower":"2,434,525,444,437,704,000,000,000,000,000,000","armyPowerText":"2.43gg","allianceId":"500394827","allianceTag":"4o77","allianceName":"ぼんじーり","allianceRole":3,"rank":3,"isOnline":0,"joinTime":1750915127,"lastShowTime":1781349327,"lastLogin":1781349327,"language":"ja","nationalflag":114,"gender":0,"usergender":0,"headFrameId":0,"source":{"map":true,"allianceMember":true},"powerRankInAlliance":39,"powerPercentileInAlliance":0.65,"powerContributionRate":0.015279,"cumulativePowerContributionRate":0.828384,"activityScore":70,"activityReasons":["map_found","recent_login_1d","high_role","alliance_member_confirmed"],"activityGrade":"ACTIVE","userStatus":"ACTIVE","inactiveScore":0,"inactiveReasons":["lastLoginWithin1Day"],"lastLoginDaysAgo":0.35},{"uid":"9035138764781","username":"ふふたん","nickname":"ふふたん","serverId":4077,"worldId":1,"x":368,"y":396,"pointId":202937,"pointType":1,"level":94,"power":27131602,"armyPower":"14,783,451,603,007,454,000,000,000,000,000,000","armyPowerText":"14.8gg","allianceId":"500394827","allianceTag":"4o77","allianceName":"ぼんじーり","allianceRole":3,"rank":3,"isOnline":0,"joinTime":1755231505,"lastShowTime":1781370564,"lastLogin":1781370564,"language":"ja","nationalflag":-1,"gender":0,"usergender":2,"headFrameId":40,"source":{"map":true,"allianceMember":true},"powerRankInAlliance":40,"powerPercentileInAlliance":0.6667,"powerContributionRate":0.015206,"cumulativePowerContributionRate":0.84359,"activityScore":70,"activityReasons":["map_found","recent_login_1d","high_role","alliance_member_confirmed"],"activityGrade":"ACTIVE","userStatus":"ACTIVE","inactiveScore":0,"inactiveReasons":["lastLoginWithin1Day"],"lastLoginDaysAgo":0.11},{"uid":"9046894055405","username":"水瓶座のつん","nickname":"水瓶座のつん","serverId":4077,"worldId":1,"x":420,"y":628,"pointId":321747,"pointType":1,"level":90,"power":26046132,"armyPower":"1","armyPowerText":"1","allianceId":"500394827","allianceTag":"4o77","allianceName":"ぼんじーり","allianceRole":3,"rank":3,"isOnline":0,"joinTime":1750929292,"lastShowTime":1781254516,"lastLogin":1781254516,"language":"ja","nationalflag":114,"gender":0,"usergender":2,"headFrameId":72,"source":{"map":true,"allianceMember":true},"powerRankInAlliance":41,"powerPercentileInAlliance":0.6833,"powerContributionRate":0.014598,"cumulativePowerContributionRate":0.858188,"activityScore":65,"activityReasons":["map_found","recent_login_3d","high_role","alliance_member_confirmed"],"activityGrade":"ACTIVE","userStatus":"RECENT","inactiveScore":10,"inactiveReasons":["lastLoginWithin3Days"],"lastLoginDaysAgo":1.45},{"uid":"9067755442180","username":"K1z5_s1","nickname":"K1z5_s1","serverId":4077,"worldId":1,"x":448,"y":634,"pointId":324833,"pointType":1,"level":100,"power":25864101,"armyPower":"807,657,507,380,210,500,000,000,000,000,000,000","armyPowerText":"808gg","allianceId":"500394827","allianceTag":"4o77","allianceName":"ぼんじーり","allianceRole":2,"rank":2,"isOnline":0,"joinTime":1769346712,"lastShowTime":1781281421,"lastLogin":1781281421,"language":"ja","nationalflag":114,"gender":0,"usergender":2,"headFrameId":157,"source":{"map":true,"allianceMember":true},"powerRankInAlliance":42,"powerPercentileInAlliance":0.7,"powerContributionRate":0.014496,"cumulativePowerContributionRate":0.872684,"activityScore":65,"activityReasons":["map_found","recent_login_3d","high_role","alliance_member_confirmed"],"activityGrade":"ACTIVE","userStatus":"RECENT","inactiveScore":10,"inactiveReasons":["lastLoginWithin3Days"],"lastLoginDaysAgo":1.14},{"uid":"9045716996077","username":"SHON","nickname":"SHON","serverId":4077,"worldId":1,"x":423,"y":627,"pointId":321236,"pointType":1,"level":100,"power":24708570,"armyPower":"170,783,312,930,026,180,000,000,000,000,000,000","armyPowerText":"171gg","allianceId":"500394827","allianceTag":"4o77","allianceName":"ぼんじーり","allianceRole":3,"rank":3,"isOnline":0,"joinTime":1748951085,"lastShowTime":1781355058,"lastLogin":1781355058,"language":"ja","nationalflag":114,"gender":0,"usergender":0,"headFrameId":157,"source":{"map":true,"allianceMember":true},"powerRankInAlliance":43,"powerPercentileInAlliance":0.7167,"powerContributionRate":0.013848,"cumulativePowerContributionRate":0.886532,"activityScore":70,"activityReasons":["map_found","recent_login_1d","high_role","alliance_member_confirmed"],"activityGrade":"ACTIVE","userStatus":"ACTIVE","inactiveScore":0,"inactiveReasons":["lastLoginWithin1Day"],"lastLoginDaysAgo":0.29},{"uid":"9093973676032","username":"ちょこあいす","nickname":"ちょこあいす","serverId":4077,"worldId":1,"x":415,"y":631,"pointId":323280,"pointType":1,"level":100,"power":22823492,"armyPower":"1","armyPowerText":"1","allianceId":"500394827","allianceTag":"4o77","allianceName":"ぼんじーり","allianceRole":4,"rank":4,"isOnline":0,"joinTime":1766927502,"lastShowTime":1781356862,"lastLogin":1781356862,"language":"ja","nationalflag":114,"gender":0,"usergender":2,"headFrameId":100,"source":{"map":true,"allianceMember":true},"powerRankInAlliance":44,"powerPercentileInAlliance":0.7333,"powerContributionRate":0.012792,"cumulativePowerContributionRate":0.899324,"activityScore":70,"activityReasons":["map_found","recent_login_1d","high_role","alliance_member_confirmed"],"activityGrade":"ACTIVE","userStatus":"ACTIVE","inactiveScore":0,"inactiveReasons":["lastLoginWithin1Day"],"lastLoginDaysAgo":0.27},{"uid":"9054948823040","username":"Nico","nickname":"Nico","serverId":4077,"worldId":1,"x":448,"y":630,"pointId":322785,"pointType":1,"level":91,"power":22011347,"armyPower":"1,350,685,381,528,206,000,000,000,000,000,000","armyPowerText":"1.35gg","allianceId":"500394827","allianceTag":"4o77","allianceName":"ぼんじーり","allianceRole":3,"rank":3,"isOnline":0,"joinTime":1772535102,"lastShowTime":1781369221,"lastLogin":1781369221,"language":"ja","nationalflag":114,"gender":0,"usergender":0,"headFrameId":157,"source":{"map":true,"allianceMember":true},"powerRankInAlliance":45,"powerPercentileInAlliance":0.75,"powerContributionRate":0.012337,"cumulativePowerContributionRate":0.91166,"activityScore":70,"activityReasons":["map_found","recent_login_1d","high_role","alliance_member_confirmed"],"activityGrade":"ACTIVE","userStatus":"ACTIVE","inactiveScore":0,"inactiveReasons":["lastLoginWithin1Day"],"lastLoginDaysAgo":0.12},{"uid":"9046077411309","username":"もり男","nickname":"もり男","serverId":4077,"worldId":1,"x":340,"y":454,"pointId":232619,"pointType":1,"level":100,"power":21071964,"armyPower":"37,305,499,651,616,060,000,000,000,000,000,000","armyPowerText":"37.3gg","allianceId":"500396177","allianceTag":"l__1","allianceName":"無言ポイ活a","allianceRole":8,"rank":8,"isOnline":0,"joinTime":1752509517,"lastShowTime":1781368256,"lastLogin":1781368256,"language":"ja","nationalflag":114,"gender":0,"usergender":0,"headFrameId":157,"source":{"map":true,"allianceMember":true},"powerRankInAlliance":2,"powerPercentileInAlliance":1,"powerContributionRate":0.382172,"cumulativePowerContributionRate":1,"activityScore":60,"activityReasons":["map_found","recent_login_1d","alliance_member_confirmed"],"activityGrade":"ACTIVE","userStatus":"ACTIVE","inactiveScore":0,"inactiveReasons":["lastLoginWithin1Day"],"lastLoginDaysAgo":0.13},{"uid":"9047828533229","username":"怒羅衛門","nickname":"怒羅衛門","serverId":4077,"worldId":1,"x":426,"y":614,"pointId":314582,"pointType":1,"level":100,"power":19782332,"armyPower":"254,653,601,900,497,700,000,000,000,000,000,000","armyPowerText":"255gg","allianceId":"500394827","allianceTag":"4o77","allianceName":"ぼんじーり","allianceRole":3,"rank":3,"isOnline":0,"joinTime":1749475228,"lastShowTime":1781365191,"lastLogin":1781365191,"language":"ja","nationalflag":114,"gender":0,"usergender":0,"headFrameId":1,"source":{"map":true,"allianceMember":true},"powerRankInAlliance":46,"powerPercentileInAlliance":0.7667,"powerContributionRate":0.011087,"cumulativePowerContributionRate":0.922748,"activityScore":70,"activityReasons":["map_found","recent_login_1d","high_role","alliance_member_confirmed"],"activityGrade":"ACTIVE","userStatus":"ACTIVE","inactiveScore":0,"inactiveReasons":["lastLoginWithin1Day"],"lastLoginDaysAgo":0.17},{"uid":"9312295030765","username":"serigala","nickname":"serigala","serverId":4077,"worldId":1,"x":236,"y":250,"pointId":128119,"pointType":1,"level":100,"power":19471165,"armyPower":"258,868,652,982,657,400,000,000,000,000,000,000","armyPowerText":"259gg","allianceId":"500394827","allianceTag":"4o77","allianceName":"ぼんじーり","allianceRole":3,"rank":3,"isOnline":1,"joinTime":1771121905,"lastShowTime":1781379725,"lastLogin":1781379725,"language":"ja","nationalflag":101,"gender":0,"usergender":2,"headFrameId":0,"source":{"map":true,"allianceMember":true},"powerRankInAlliance":47,"powerPercentileInAlliance":0.7833,"powerContributionRate":0.010913,"cumulativePowerContributionRate":0.93366,"activityScore":100,"activityReasons":["map_found","online","recent_login_1d","high_role","alliance_member_confirmed"],"activityGrade":"CORE","userStatus":"ACTIVE","inactiveScore":0,"inactiveReasons":["online"],"lastLoginDaysAgo":0},{"uid":"9047536603117","username":"まう","nickname":"まう","serverId":4077,"worldId":1,"x":645,"y":273,"pointId":140099,"pointType":1,"level":87,"power":19106610,"armyPower":"16,414,946,065,902,205,000,000,000,000,000","armyPowerText":"16.4ff","allianceId":"500396289","allianceTag":"s5xA","allianceName":"グランteamA","allianceRole":8,"rank":8,"isOnline":0,"joinTime":1751183398,"lastShowTime":1781363538,"lastLogin":1781363538,"language":"ja","nationalflag":114,"gender":0,"usergender":0,"headFrameId":2,"source":{"map":true,"allianceMember":true},"powerRankInAlliance":3,"powerPercentileInAlliance":0.3333,"powerContributionRate":0.147353,"cumulativePowerContributionRate":0.697694,"activityScore":100,"activityReasons":["map_found","top_50_power","cumulative_power_80","recent_login_1d","alliance_member_confirmed"],"activityGrade":"CORE","userStatus":"ACTIVE","inactiveScore":0,"inactiveReasons":["lastLoginWithin1Day"],"lastLoginDaysAgo":0.19},{"uid":"9266524524548","username":"海老天のしっぽ","nickname":"海老天のしっぽ","serverId":4077,"worldId":1,"x":433,"y":621,"pointId":318169,"pointType":1,"level":97,"power":18405040,"armyPower":"52,049,366,361,492,810,000,000,000,000,000,000","armyPowerText":"52gg","allianceId":"500394827","allianceTag":"4o77","allianceName":"ぼんじーり","allianceRole":3,"rank":3,"isOnline":0,"joinTime":1779290641,"lastShowTime":1781368603,"lastLogin":1781368603,"language":"ja","nationalflag":114,"gender":0,"usergender":0,"headFrameId":0,"source":{"map":true,"allianceMember":true},"powerRankInAlliance":48,"powerPercentileInAlliance":0.8,"powerContributionRate":0.010315,"cumulativePowerContributionRate":0.943976,"activityScore":70,"activityReasons":["map_found","recent_login_1d","high_role","alliance_member_confirmed"],"activityGrade":"ACTIVE","userStatus":"ACTIVE","inactiveScore":0,"inactiveReasons":["lastLoginWithin1Day"],"lastLoginDaysAgo":0.13},{"uid":"9035863330797","username":"ひげ","nickname":"ひげ","serverId":4077,"worldId":1,"x":93,"y":263,"pointId":134703,"pointType":1,"level":90,"power":17756456,"armyPower":"151,296,029,462,862,790,000,000,000,000,000","armyPowerText":"151ff","allianceId":"500395207","allianceTag":"Hkr2","allianceName":"柊連盟セカンド","allianceRole":1,"rank":1,"isOnline":0,"joinTime":1746188484,"lastShowTime":1781046189,"lastLogin":1781046189,"language":"ja","nationalflag":114,"gender":0,"usergender":0,"headFrameId":0,"source":{"map":true,"allianceMember":true},"powerRankInAlliance":1,"powerPercentileInAlliance":0.5,"powerContributionRate":0.925256,"cumulativePowerContributionRate":0.925256,"activityScore":70,"activityReasons":["map_found","top_50_power","recent_login_7d","high_role","alliance_member_confirmed"],"activityGrade":"ACTIVE","userStatus":"SLEEPY","inactiveScore":35,"inactiveReasons":["lastLoginWithin7Days"],"lastLoginDaysAgo":3.86},{"uid":"9365582516205","username":"さぶ間隔","nickname":"さぶ間隔","serverId":4077,"worldId":1,"x":433,"y":641,"pointId":328409,"pointType":1,"level":90,"power":16525326,"armyPower":"617,816,841,880,132,000,000,000,000,000,000","armyPowerText":"618ff","allianceId":"500394827","allianceTag":"4o77","allianceName":"ぼんじーり","allianceRole":3,"rank":3,"isOnline":0,"joinTime":1765289347,"lastShowTime":1781364641,"lastLogin":1781364641,"language":"ja","nationalflag":114,"gender":0,"usergender":0,"headFrameId":0,"source":{"map":true,"allianceMember":true},"powerRankInAlliance":49,"powerPercentileInAlliance":0.8167,"powerContributionRate":0.009262,"cumulativePowerContributionRate":0.953237,"activityScore":70,"activityReasons":["map_found","recent_login_1d","high_role","alliance_member_confirmed"],"activityGrade":"ACTIVE","userStatus":"ACTIVE","inactiveScore":0,"inactiveReasons":["lastLoginWithin1Day"],"lastLoginDaysAgo":0.18},{"uid":"9116383350765","username":"ネス湖のてっペん","nickname":"ネス湖のてっペん","serverId":4077,"worldId":1,"x":436,"y":636,"pointId":325851,"pointType":1,"level":80,"power":13746175,"armyPower":"17,801,790,814,594,560,000,000,000,000","armyPowerText":"17.8ee","allianceId":"500394827","allianceTag":"4o77","allianceName":"ぼんじーり","allianceRole":4,"rank":4,"isOnline":0,"joinTime":1769753485,"lastShowTime":1781351389,"lastLogin":1781351389,"language":"ja","nationalflag":203,"gender":0,"usergender":0,"headFrameId":0,"source":{"map":true,"allianceMember":true},"powerRankInAlliance":50,"powerPercentileInAlliance":0.8333,"powerContributionRate":0.007704,"cumulativePowerContributionRate":0.960942,"activityScore":70,"activityReasons":["map_found","recent_login_1d","high_role","alliance_member_confirmed"],"activityGrade":"ACTIVE","userStatus":"ACTIVE","inactiveScore":0,"inactiveReasons":["lastLoginWithin1Day"],"lastLoginDaysAgo":0.33},{"uid":"9046908178413","username":"コージ2","nickname":"コージ2","serverId":4077,"worldId":1,"x":316,"y":572,"pointId":293023,"pointType":1,"level":84,"power":13023545,"armyPower":"2,393,150,997,064,977,800,000,000,000,000","armyPowerText":"2.39ff","allianceId":"500396213","allianceTag":"#hrg","allianceName":"風鈴月下","allianceRole":6,"rank":6,"isOnline":0,"joinTime":1746531801,"lastShowTime":1781346219,"lastLogin":1781346219,"language":"ja","nationalflag":114,"gender":0,"usergender":0,"headFrameId":1,"source":{"map":true,"allianceMember":true},"powerRankInAlliance":1,"powerPercentileInAlliance":0.5,"powerContributionRate":0.537705,"cumulativePowerContributionRate":0.537705,"activityScore":100,"activityReasons":["map_found","top_50_power","cumulative_power_80","recent_login_1d","alliance_member_confirmed"],"activityGrade":"CORE","userStatus":"ACTIVE","inactiveScore":0,"inactiveReasons":["lastLoginWithin1Day"],"lastLoginDaysAgo":0.39},{"uid":"9040904523757","username":"通りすがりの人","serverId":4077,"worldId":4077,"x":519,"y":507,"pointId":259844,"pointType":1,"level":78,"power":12820810,"armyPower":"1","armyPowerText":"1","allianceId":"500397233","allianceTag":"sho4","language":"ja","nationalflag":114,"gender":0,"usergender":0,"source":{"map":true},"powerRankInAlliance":1,"powerPercentileInAlliance":1,"powerContributionRate":1,"cumulativePowerContributionRate":1,"activityScore":30,"activityReasons":["map_found"],"activityGrade":"WATCH","userStatus":"UNKNOWN","inactiveScore":0,"inactiveReasons":["lastLogin_unknown"],"lastLoginDaysAgo":null},{"uid":"9035714924525","username":"うどんフェレット","nickname":"うどんフェレット","serverId":4077,"worldId":1,"x":439,"y":623,"pointId":319196,"pointType":1,"level":85,"power":12725694,"armyPower":"1","armyPowerText":"1","allianceId":"500394827","allianceTag":"4o77","allianceName":"ぼんじーり","allianceRole":3,"rank":3,"isOnline":0,"joinTime":1749122356,"lastShowTime":1781300887,"lastLogin":1781300887,"language":"ja","nationalflag":114,"gender":0,"usergender":0,"headFrameId":157,"source":{"map":true,"allianceMember":true},"powerRankInAlliance":51,"powerPercentileInAlliance":0.85,"powerContributionRate":0.007132,"cumulativePowerContributionRate":0.968074,"activityScore":70,"activityReasons":["map_found","recent_login_1d","high_role","alliance_member_confirmed"],"activityGrade":"ACTIVE","userStatus":"ACTIVE","inactiveScore":0,"inactiveReasons":["lastLoginWithin1Day"],"lastLoginDaysAgo":0.91},{"uid":"9116014776301","username":"MN8⁴⁰⁷⁷","nickname":"MN8⁴⁰⁷⁷","serverId":4077,"worldId":1,"x":413,"y":485,"pointId":248527,"pointType":1,"level":80,"power":12018914,"armyPower":"79,508,458,351,160,950,000,000,000,000","armyPowerText":"79.5ee","allianceId":"500394827","allianceTag":"4o77","allianceName":"ぼんじーり","allianceRole":3,"rank":3,"isOnline":0,"joinTime":1765492386,"lastShowTime":1781354977,"lastLogin":1781354977,"language":"ja","nationalflag":114,"gender":0,"usergender":0,"headFrameId":0,"source":{"map":true,"allianceMember":true},"powerRankInAlliance":52,"powerPercentileInAlliance":0.8667,"powerContributionRate":0.006736,"cumulativePowerContributionRate":0.97481,"activityScore":70,"activityReasons":["map_found","recent_login_1d","high_role","alliance_member_confirmed"],"activityGrade":"ACTIVE","userStatus":"ACTIVE","inactiveScore":0,"inactiveReasons":["lastLoginWithin1Day"],"lastLoginDaysAgo":0.29},{"uid":"9116188676077","username":"Kozy","nickname":"Kozy","serverId":4077,"worldId":1,"x":318,"y":574,"pointId":294048,"pointType":1,"level":79,"power":11197047,"armyPower":"49,838,462,104,884,260,000,000,000,000","armyPowerText":"49.8ee","allianceId":"500396213","allianceTag":"#hrg","allianceName":"風鈴月下","allianceRole":4,"rank":4,"isOnline":0,"joinTime":1750623533,"lastShowTime":1781346214,"lastLogin":1781346214,"language":"ja","nationalflag":114,"gender":0,"usergender":0,"headFrameId":1,"source":{"map":true,"allianceMember":true},"powerRankInAlliance":2,"powerPercentileInAlliance":1,"powerContributionRate":0.462295,"cumulativePowerContributionRate":1,"activityScore":70,"activityReasons":["map_found","recent_login_1d","high_role","alliance_member_confirmed"],"activityGrade":"ACTIVE","userStatus":"ACTIVE","inactiveScore":0,"inactiveReasons":["lastLoginWithin1Day"],"lastLoginDaysAgo":0.39},{"uid":"9350880923629","username":"あん","nickname":"あん","serverId":4077,"worldId":1,"x":665,"y":265,"pointId":136013,"pointType":1,"level":75,"power":10974614,"armyPower":"40,912,444,040,006,510,000,000,000","armyPowerText":"40.9dd","allianceId":"500396289","allianceTag":"s5xA","allianceName":"グランteamA","allianceRole":3,"rank":3,"isOnline":0,"joinTime":1767526623,"lastShowTime":1781278792,"lastLogin":1781278792,"language":"ja","nationalflag":114,"gender":0,"usergender":0,"headFrameId":0,"source":{"map":true,"allianceMember":true},"powerRankInAlliance":4,"powerPercentileInAlliance":0.4444,"powerContributionRate":0.084638,"cumulativePowerContributionRate":0.782331,"activityScore":105,"activityReasons":["map_found","top_50_power","cumulative_power_80","recent_login_3d","high_role","alliance_member_confirmed"],"activityGrade":"CORE","userStatus":"RECENT","inactiveScore":10,"inactiveReasons":["lastLoginWithin3Days"],"lastLoginDaysAgo":1.17},{"uid":"9043503714285","username":"タゲシ","nickname":"タゲシ","serverId":4077,"worldId":1,"x":419,"y":631,"pointId":323282,"pointType":1,"level":74,"power":9771810,"armyPower":"344,550,723,249,348,700,000,000,000","armyPowerText":"345dd","allianceId":"500394827","allianceTag":"4o77","allianceName":"ぼんじーり","allianceRole":3,"rank":3,"isOnline":0,"joinTime":1755435794,"lastShowTime":1781353857,"lastLogin":1781353857,"language":"ja","nationalflag":114,"gender":0,"usergender":1,"headFrameId":157,"source":{"map":true,"allianceMember":true},"powerRankInAlliance":53,"powerPercentileInAlliance":0.8833,"powerContributionRate":0.005477,"cumulativePowerContributionRate":0.980287,"activityScore":70,"activityReasons":["map_found","recent_login_1d","high_role","alliance_member_confirmed"],"activityGrade":"ACTIVE","userStatus":"ACTIVE","inactiveScore":0,"inactiveReasons":["lastLoginWithin1Day"],"lastLoginDaysAgo":0.3},{"uid":"9064949518317","username":"える","nickname":"える","serverId":4077,"worldId":1,"x":429,"y":645,"pointId":330455,"pointType":1,"level":80,"power":9662038,"armyPower":"6,694,184,684,917,303,000,000,000,000","armyPowerText":"6.69ee","allianceId":"500394827","allianceTag":"4o77","allianceName":"ぼんじーり","allianceRole":2,"rank":2,"isOnline":0,"joinTime":1748708850,"lastShowTime":1781110388,"lastLogin":1781110388,"language":"ja","nationalflag":114,"gender":0,"usergender":0,"headFrameId":2,"source":{"map":true,"allianceMember":true},"powerRankInAlliance":54,"powerPercentileInAlliance":0.9,"powerContributionRate":0.005415,"cumulativePowerContributionRate":0.985702,"activityScore":55,"activityReasons":["map_found","recent_login_7d","high_role","alliance_member_confirmed"],"activityGrade":"ACTIVE","userStatus":"SLEEPY","inactiveScore":35,"inactiveReasons":["lastLoginWithin7Days"],"lastLoginDaysAgo":3.12},{"uid":"9045231079405","username":"アロエ","nickname":"アロエ","serverId":4077,"worldId":1,"x":663,"y":259,"pointId":132940,"pointType":1,"level":76,"power":9133352,"armyPower":"198,244,950,618,703,100,000,000,000","armyPowerText":"198dd","allianceId":"500396289","allianceTag":"s5xA","allianceName":"グランteamA","allianceRole":7,"rank":7,"isOnline":0,"joinTime":1751208641,"lastShowTime":1781167501,"lastLogin":1781167501,"language":"ja","nationalflag":114,"gender":0,"usergender":2,"headFrameId":0,"source":{"map":true,"allianceMember":true},"powerRankInAlliance":5,"powerPercentileInAlliance":0.5556,"powerContributionRate":0.070438,"cumulativePowerContributionRate":0.852769,"activityScore":55,"activityReasons":["map_found","recent_login_3d","alliance_member_confirmed"],"activityGrade":"ACTIVE","userStatus":"RECENT","inactiveScore":10,"inactiveReasons":["lastLoginWithin3Days"],"lastLoginDaysAgo":2.46},{"uid":"9036502306797","username":"wy.9036502306797","serverId":4077,"worldId":4077,"x":348,"y":584,"pointId":299183,"pointType":1,"level":81,"power":8558532,"armyPower":"222,387,167,248,885,700,000,000,000,000","armyPowerText":"222ee","allianceId":"500395057","allianceTag":"l@cc","language":"ja","nationalflag":114,"gender":0,"usergender":0,"source":{"map":true},"powerRankInAlliance":1,"powerPercentileInAlliance":1,"powerContributionRate":1,"cumulativePowerContributionRate":1,"activityScore":30,"activityReasons":["map_found"],"activityGrade":"WATCH","userStatus":"UNKNOWN","inactiveScore":0,"inactiveReasons":["lastLogin_unknown"],"lastLoginDaysAgo":null},{"uid":"9043250221037","username":"神の追跡者","nickname":"神の追跡者","serverId":4077,"worldId":1,"x":664,"y":260,"pointId":133453,"pointType":1,"level":75,"power":8390856,"armyPower":"715,265,438,412,271,300,000,000,000","armyPowerText":"715dd","allianceId":"500396289","allianceTag":"s5xA","allianceName":"グランteamA","allianceRole":3,"rank":3,"isOnline":0,"joinTime":1766293917,"lastShowTime":1781324320,"lastLogin":1781324320,"language":"ja","nationalflag":114,"gender":0,"usergender":0,"headFrameId":0,"source":{"map":true,"allianceMember":true},"powerRankInAlliance":6,"powerPercentileInAlliance":0.6667,"powerContributionRate":0.064711,"cumulativePowerContributionRate":0.917481,"activityScore":70,"activityReasons":["map_found","recent_login_1d","high_role","alliance_member_confirmed"],"activityGrade":"ACTIVE","userStatus":"ACTIVE","inactiveScore":0,"inactiveReasons":["lastLoginWithin1Day"],"lastLoginDaysAgo":0.64},{"uid":"9036329258989","username":"wy.9036329258989","serverId":4077,"worldId":4077,"x":503,"y":499,"pointId":255740,"pointType":1,"level":81,"power":8012107,"armyPower":"89,476,991,461,493,690,000,000,000,000","armyPowerText":"89.5ee","allianceId":"500394844","allianceTag":"NOKU","language":"ja","nationalflag":114,"gender":0,"usergender":0,"source":{"map":true},"powerRankInAlliance":1,"powerPercentileInAlliance":1,"powerContributionRate":1,"cumulativePowerContributionRate":1,"activityScore":30,"activityReasons":["map_found"],"activityGrade":"WATCH","userStatus":"UNKNOWN","inactiveScore":0,"inactiveReasons":["lastLogin_unknown"],"lastLoginDaysAgo":null},{"uid":"9087031775236","username":"鳩のフン","nickname":"鳩のフン","serverId":4077,"worldId":1,"x":364,"y":398,"pointId":203959,"pointType":1,"level":85,"power":7456590,"armyPower":"2,519,759,660,835,335,700,000,000,000,000","armyPowerText":"2.52ff","allianceId":"500394827","allianceTag":"4o77","allianceName":"ぼんじーり","allianceRole":3,"rank":3,"isOnline":0,"joinTime":1779282428,"lastShowTime":1780841326,"lastLogin":1780841326,"language":"ja","nationalflag":114,"gender":0,"usergender":0,"headFrameId":0,"source":{"map":true,"allianceMember":true},"powerRankInAlliance":55,"powerPercentileInAlliance":0.9167,"powerContributionRate":0.004179,"cumulativePowerContributionRate":0.989881,"activityScore":55,"activityReasons":["map_found","recent_login_7d","high_role","alliance_member_confirmed"],"activityGrade":"ACTIVE","userStatus":"SLEEPY","inactiveScore":35,"inactiveReasons":["lastLoginWithin7Days"],"lastLoginDaysAgo":6.23},{"uid":"9045709164525","username":"ふふたそ","nickname":"ふふたそ","serverId":4077,"worldId":1,"x":348,"y":888,"pointId":454831,"pointType":1,"level":62,"power":6492889,"armyPower":"55,595,172,171,909,120,000,000","armyPowerText":"55.6cc","allianceId":"500394827","allianceTag":"4o77","allianceName":"ぼんじーり","allianceRole":2,"rank":2,"isOnline":0,"joinTime":1763207986,"lastShowTime":1781176255,"lastLogin":1781176255,"language":"ja","nationalflag":114,"gender":0,"usergender":2,"headFrameId":1,"source":{"map":true,"allianceMember":true},"powerRankInAlliance":56,"powerPercentileInAlliance":0.9333,"powerContributionRate":0.003639,"cumulativePowerContributionRate":0.99352,"activityScore":65,"activityReasons":["map_found","recent_login_3d","high_role","alliance_member_confirmed"],"activityGrade":"ACTIVE","userStatus":"RECENT","inactiveScore":10,"inactiveReasons":["lastLoginWithin3Days"],"lastLoginDaysAgo":2.36},{"uid":"9047512387565","username":"りんりん","nickname":"りんりん","serverId":4077,"worldId":1,"x":665,"y":261,"pointId":133965,"pointType":1,"level":70,"power":6008933,"armyPower":"20,119,956,790,124,040,000,000,000","armyPowerText":"20.1dd","allianceId":"500396289","allianceTag":"s5xA","allianceName":"グランteamA","allianceRole":3,"rank":3,"isOnline":0,"joinTime":1752310656,"lastShowTime":1781336157,"lastLogin":1781336157,"language":"ja","nationalflag":114,"gender":0,"usergender":0,"headFrameId":1,"source":{"map":true,"allianceMember":true},"powerRankInAlliance":7,"powerPercentileInAlliance":0.7778,"powerContributionRate":0.046342,"cumulativePowerContributionRate":0.963822,"activityScore":70,"activityReasons":["map_found","recent_login_1d","high_role","alliance_member_confirmed"],"activityGrade":"ACTIVE","userStatus":"ACTIVE","inactiveScore":0,"inactiveReasons":["lastLoginWithin1Day"],"lastLoginDaysAgo":0.51},{"uid":"9233043066861","username":"まひろ","nickname":"まひろ","serverId":4077,"worldId":1,"x":434,"y":648,"pointId":331994,"pointType":1,"level":68,"power":5824786,"armyPower":"3,393,170,318,179,700,000,000,000","armyPowerText":"3.39dd","allianceId":"500394827","allianceTag":"4o77","allianceName":"ぼんじーり","allianceRole":3,"rank":3,"isOnline":0,"joinTime":1762596238,"lastShowTime":1781365227,"lastLogin":1781365227,"language":"ja","nationalflag":114,"gender":0,"usergender":2,"headFrameId":0,"source":{"map":true,"allianceMember":true},"powerRankInAlliance":57,"powerPercentileInAlliance":0.95,"powerContributionRate":0.003265,"cumulativePowerContributionRate":0.996785,"activityScore":70,"activityReasons":["map_found","recent_login_1d","high_role","alliance_member_confirmed"],"activityGrade":"ACTIVE","userStatus":"ACTIVE","inactiveScore":0,"inactiveReasons":["lastLoginWithin1Day"],"lastLoginDaysAgo":0.17},{"uid":"9492061556717","username":"ボスP","nickname":"ボスP","serverId":4077,"worldId":1,"x":531,"y":897,"pointId":459530,"pointType":1,"level":61,"power":4690415,"armyPower":"12,051,511,902,970,132,000,000","armyPowerText":"12.1cc","allianceId":"500396289","allianceTag":"s5xA","allianceName":"グランteamA","allianceRole":3,"rank":3,"isOnline":0,"joinTime":1769850538,"lastShowTime":1781042345,"lastLogin":1781042345,"language":"ja","nationalflag":114,"gender":0,"usergender":2,"headFrameId":0,"source":{"map":true,"allianceMember":true},"powerRankInAlliance":8,"powerPercentileInAlliance":0.8889,"powerContributionRate":0.036173,"cumulativePowerContributionRate":0.999995,"activityScore":55,"activityReasons":["map_found","recent_login_7d","high_role","alliance_member_confirmed"],"activityGrade":"ACTIVE","userStatus":"SLEEPY","inactiveScore":35,"inactiveReasons":["lastLoginWithin7Days"],"lastLoginDaysAgo":3.91},{"uid":"9042230710253","username":"키작은소녀","serverId":4077,"worldId":4077,"x":307,"y":769,"pointId":393882,"pointType":1,"level":54,"power":3452309,"armyPower":"18,841,299,154,244,903,000","armyPowerText":"18.8bb","allianceId":"500395775","allianceTag":"aeon","language":"gk","nationalflag":114,"gender":0,"usergender":0,"source":{"map":true},"powerRankInAlliance":1,"powerPercentileInAlliance":1,"powerContributionRate":1,"cumulativePowerContributionRate":1,"activityScore":30,"activityReasons":["map_found"],"activityGrade":"WATCH","userStatus":"UNKNOWN","inactiveScore":0,"inactiveReasons":["lastLogin_unknown"],"lastLoginDaysAgo":null},{"uid":"9037364137965","username":"アークルーラー","serverId":4077,"worldId":4077,"x":501,"y":199,"pointId":102139,"pointType":1,"level":62,"power":2733085,"armyPower":"4,931,352,643,709,474,000,000","armyPowerText":"4.93cc","allianceId":"500394849","allianceTag":";%%x","language":"ja","nationalflag":114,"gender":0,"usergender":0,"source":{"map":true},"powerRankInAlliance":1,"powerPercentileInAlliance":1,"powerContributionRate":1,"cumulativePowerContributionRate":1,"activityScore":30,"activityReasons":["map_found"],"activityGrade":"WATCH","userStatus":"UNKNOWN","inactiveScore":0,"inactiveReasons":["lastLogin_unknown"],"lastLoginDaysAgo":null},{"uid":"9270172192749","username":"めにゃ","nickname":"めにゃ","serverId":4077,"worldId":1,"x":435,"y":647,"pointId":331482,"pointType":1,"level":51,"power":2205452,"armyPower":"2,153,851,559,862,306,000","armyPowerText":"2.15bb","allianceId":"500394827","allianceTag":"4o77","allianceName":"ぼんじーり","allianceRole":3,"rank":3,"isOnline":0,"joinTime":1777955342,"lastShowTime":1781350944,"lastLogin":1781350944,"language":"ja","nationalflag":114,"gender":0,"usergender":0,"headFrameId":0,"source":{"map":true,"allianceMember":true},"powerRankInAlliance":58,"powerPercentileInAlliance":0.9667,"powerContributionRate":0.001236,"cumulativePowerContributionRate":0.998021,"activityScore":70,"activityReasons":["map_found","recent_login_1d","high_role","alliance_member_confirmed"],"activityGrade":"ACTIVE","userStatus":"ACTIVE","inactiveScore":0,"inactiveReasons":["lastLoginWithin1Day"],"lastLoginDaysAgo":0.33},{"uid":"9203182604269","username":"ACAね","serverId":4077,"worldId":4077,"x":458,"y":52,"pointId":26854,"pointType":1,"level":46,"power":2150565,"armyPower":"6,692,425,129,163,308","armyPowerText":"6.69aa","allianceId":"500396250","allianceTag":"Ztmy","language":"ja","nationalflag":203,"gender":0,"usergender":2,"source":{"map":true},"powerRankInAlliance":1,"powerPercentileInAlliance":0.5,"powerContributionRate":0.623814,"cumulativePowerContributionRate":0.623814,"activityScore":70,"activityReasons":["map_found","top_50_power","cumulative_power_80"],"activityGrade":"ACTIVE","userStatus":"UNKNOWN","inactiveScore":0,"inactiveReasons":["lastLogin_unknown"],"lastLoginDaysAgo":null},{"uid":"9558887862253","username":"サブ間隔","nickname":"サブ間隔","serverId":4077,"worldId":1,"x":437,"y":637,"pointId":326363,"pointType":1,"level":57,"power":2089870,"armyPower":"144,992,802,610,646,750,000","armyPowerText":"145bb","allianceId":"500394827","allianceTag":"4o77","allianceName":"ぼんじーり","allianceRole":3,"rank":3,"isOnline":0,"joinTime":1772523562,"lastShowTime":1781364706,"lastLogin":1781364706,"language":"ja","nationalflag":114,"gender":0,"usergender":0,"headFrameId":0,"source":{"map":true,"allianceMember":true},"powerRankInAlliance":59,"powerPercentileInAlliance":0.9833,"powerContributionRate":0.001171,"cumulativePowerContributionRate":0.999192,"activityScore":70,"activityReasons":["map_found","recent_login_1d","high_role","alliance_member_confirmed"],"activityGrade":"ACTIVE","userStatus":"ACTIVE","inactiveScore":0,"inactiveReasons":["lastLoginWithin1Day"],"lastLoginDaysAgo":0.18},{"uid":"9456594259949","username":"ラッキー係長❤","serverId":4077,"worldId":4077,"x":408,"y":510,"pointId":261325,"pointType":1,"level":46,"power":1804865,"armyPower":"15,684,516,234,631,786","armyPowerText":"15.7aa","language":"ja","nationalflag":114,"gender":0,"usergender":0,"source":{"map":true},"userStatus":"UNKNOWN","inactiveScore":0,"inactiveReasons":["lastLogin_unknown"],"lastLoginDaysAgo":null},{"uid":"9510405509101","username":"にも＠偽物","nickname":"にも＠偽物","serverId":4077,"worldId":1,"x":432,"y":650,"pointId":333017,"pointType":1,"level":41,"power":1441510,"armyPower":"1,762,103,227","armyPowerText":"1.76B","allianceId":"500394827","allianceTag":"4o77","allianceName":"ぼんじーり","allianceRole":3,"rank":3,"isOnline":0,"joinTime":1770032711,"lastShowTime":1781353622,"lastLogin":1781353622,"language":"ja","nationalflag":114,"gender":0,"usergender":0,"headFrameId":0,"source":{"map":true,"allianceMember":true},"powerRankInAlliance":60,"powerPercentileInAlliance":1,"powerContributionRate":0.000808,"cumulativePowerContributionRate":1,"activityScore":70,"activityReasons":["map_found","recent_login_1d","high_role","alliance_member_confirmed"],"activityGrade":"ACTIVE","userStatus":"ACTIVE","inactiveScore":0,"inactiveReasons":["lastLoginWithin1Day"],"lastLoginDaysAgo":0.3},{"uid":"9043219910637","username":"ばななさん","nickname":"ばななさん","serverId":4077,"worldId":1,"x":164,"y":276,"pointId":141395,"pointType":1,"level":37,"power":1434400,"armyPower":"61,389,301,547,235","armyPowerText":"61.4T","allianceId":"500395207","allianceTag":"Hkr2","allianceName":"柊連盟セカンド","allianceRole":1,"rank":1,"isOnline":0,"joinTime":1779096145,"lastShowTime":1780903754,"lastLogin":1780903754,"language":"ja","nationalflag":114,"gender":0,"usergender":0,"headFrameId":116,"source":{"map":true,"allianceMember":true},"powerRankInAlliance":2,"powerPercentileInAlliance":1,"powerContributionRate":0.074744,"cumulativePowerContributionRate":1,"activityScore":55,"activityReasons":["map_found","recent_login_7d","high_role","alliance_member_confirmed"],"activityGrade":"ACTIVE","userStatus":"SLEEPY","inactiveScore":35,"inactiveReasons":["lastLoginWithin7Days"],"lastLoginDaysAgo":5.51},{"uid":"9037070340077","username":"hjk","serverId":4077,"worldId":4077,"x":419,"y":351,"pointId":179922,"pointType":1,"level":45,"power":1296880,"armyPower":"25,313,765,236,694,908","armyPowerText":"25.3aa","allianceId":"500396250","allianceTag":"Ztmy","language":"ja","nationalflag":114,"gender":0,"usergender":0,"source":{"map":true},"powerRankInAlliance":2,"powerPercentileInAlliance":1,"powerContributionRate":0.376186,"cumulativePowerContributionRate":1,"activityScore":30,"activityReasons":["map_found"],"activityGrade":"WATCH","userStatus":"UNKNOWN","inactiveScore":0,"inactiveReasons":["lastLogin_unknown"],"lastLoginDaysAgo":null},{"uid":"9035149021165","username":"すず","serverId":4077,"worldId":4077,"x":206,"y":290,"pointId":148584,"pointType":1,"level":35,"power":1137830,"armyPower":"15,839,472,980","armyPowerText":"15.8B","language":"ja","nationalflag":114,"gender":0,"usergender":2,"source":{"map":true},"userStatus":"UNKNOWN","inactiveScore":0,"inactiveReasons":["lastLogin_unknown"],"lastLoginDaysAgo":null},{"uid":"9037382488045","username":"kyo2nd","serverId":4077,"worldId":4077,"x":301,"y":727,"pointId":372375,"pointType":1,"level":34,"power":985555,"armyPower":"8,154,413,292,621","armyPowerText":"8.15T","allianceId":"500402635","allianceTag":"p01t","language":"ja","nationalflag":114,"gender":0,"usergender":0,"source":{"map":true},"powerRankInAlliance":1,"powerPercentileInAlliance":1,"powerContributionRate":1,"cumulativePowerContributionRate":1,"activityScore":30,"activityReasons":["map_found"],"activityGrade":"WATCH","userStatus":"UNKNOWN","inactiveScore":0,"inactiveReasons":["lastLogin_unknown"],"lastLoginDaysAgo":null},{"uid":"9040364277741","username":"wy.9040364277741","serverId":4077,"worldId":4077,"x":302,"y":124,"pointId":63640,"pointType":1,"level":20,"power":183560,"armyPower":"8,527,909","armyPowerText":"8.53M","language":"ge","nationalflag":114,"gender":0,"usergender":0,"source":{"map":true},"userStatus":"UNKNOWN","inactiveScore":0,"inactiveReasons":["lastLogin_unknown"],"lastLoginDaysAgo":null},{"uid":"9046969454573","username":"wy.9046969454573","serverId":4077,"worldId":4077,"x":131,"y":715,"pointId":366146,"pointType":1,"level":17,"power":124690,"armyPower":"3,472,742","armyPowerText":"3.47M","allianceId":"500396627","allianceTag":"LVU.","language":"ja","nationalflag":114,"gender":0,"usergender":0,"source":{"map":true},"powerRankInAlliance":1,"powerPercentileInAlliance":1,"powerContributionRate":1,"cumulativePowerContributionRate":1,"activityScore":30,"activityReasons":["map_found"],"activityGrade":"WATCH","userStatus":"UNKNOWN","inactiveScore":0,"inactiveReasons":["lastLogin_unknown"],"lastLoginDaysAgo":null},{"uid":"9035054780397","username":"wy.9035054780397","serverId":4077,"worldId":4077,"x":677,"y":685,"pointId":351059,"pointType":1,"level":17,"power":106310,"armyPower":"13,992,530","armyPowerText":"14M","allianceId":"500433110","allianceTag":"stpc","language":"ja","nationalflag":114,"gender":0,"usergender":0,"source":{"map":true},"powerRankInAlliance":1,"powerPercentileInAlliance":1,"powerContributionRate":1,"cumulativePowerContributionRate":1,"activityScore":30,"activityReasons":["map_found"],"activityGrade":"WATCH","userStatus":"UNKNOWN","inactiveScore":0,"inactiveReasons":["lastLogin_unknown"],"lastLoginDaysAgo":null},{"uid":"9036045783021","username":"wy.9036045783021","serverId":4077,"worldId":4077,"x":453,"y":823,"pointId":421603,"pointType":1,"level":15,"power":105045,"armyPower":"1,419,276","armyPowerText":"1.42M","language":"ja","nationalflag":114,"gender":0,"usergender":0,"source":{"map":true},"userStatus":"UNKNOWN","inactiveScore":0,"inactiveReasons":["lastLogin_unknown"],"lastLoginDaysAgo":null},{"uid":"9060934619117","username":"牛タン100人前","nickname":"牛タン100人前","serverId":4077,"worldId":1,"x":653,"y":263,"pointId":134983,"pointType":1,"level":23,"power":585,"armyPower":"550","armyPowerText":"550","allianceId":"500396289","allianceTag":"s5xA","allianceName":"グランteamA","allianceRole":3,"rank":3,"isOnline":0,"joinTime":1756824221,"lastShowTime":1781345256,"lastLogin":1781345256,"language":"ja","nationalflag":114,"gender":0,"usergender":0,"headFrameId":0,"source":{"map":true,"allianceMember":true},"powerRankInAlliance":9,"powerPercentileInAlliance":1,"powerContributionRate":0.000005,"cumulativePowerContributionRate":1,"activityScore":70,"activityReasons":["map_found","recent_login_1d","high_role","alliance_member_confirmed"],"activityGrade":"ACTIVE","userStatus":"ACTIVE","inactiveScore":0,"inactiveReasons":["lastLoginWithin1Day"],"lastLoginDaysAgo":0.4}],"alliances":[{"memberCount":60,"allianceId":"500394827","allianceTag":"4o77","allianceCode":"4o77","allianceName":"ぼんじーり","allianceLeader":"あかさ🍫🍨","allianceLevel":5,"alliancePower":3140000000,"alliancePowerText":"3.14B","allianceMemberCountShown":168,"allianceMemberMax":170,"allianceMemberText":"168/170","serverId":4077,"activitySummary":{"collectedMapMemberCount":60,"coreCount":38,"activeCount":22,"watchCount":0,"lowCount":0,"activeTotalCount":60,"totalPower":1784243830,"corePowerSum":1442497197,"activePowerSum":1784243830,"corePowerRate":0.808464,"activePowerRate":1,"top20PowerCount":12,"cumulative80PowerCount":37,"shownMemberCount":168,"shownMemberMax":170},"activeAllianceGrade":"CORE","activeAllianceScore":100,"activeAllianceReasons":["coverageRate=35.71%","coreCount>=10","activeCount>=15","memberCount>=30","activePowerRate>=75% && coreCount>=5","corePowerRate>=50% && coreCount>=3"],"coverageRate":0.3571},{"memberCount":9,"allianceId":"500396289","allianceTag":"s5xA","allianceCode":"s5xA","allianceName":"グランteamA","allianceLeader":"白マメ","allianceLevel":3,"alliancePower":498000000,"alliancePowerText":"498M","allianceMemberCountShown":127,"allianceMemberMax":170,"allianceMemberText":"127/170","serverId":4077,"activitySummary":{"collectedMapMemberCount":9,"coreCount":4,"activeCount":5,"watchCount":0,"lowCount":0,"activeTotalCount":9,"totalPower":129665652,"corePowerSum":101441511,"activePowerSum":129665652,"corePowerRate":0.782331,"activePowerRate":1,"top20PowerCount":1,"cumulative80PowerCount":4,"shownMemberCount":127,"shownMemberMax":170},"activeAllianceGrade":"INSUFFICIENT","activeAllianceScore":0,"activeAllianceReasons":["coverageRate=7.09%","coverageRate<10%","sample_too_small_for_alliance_grade"],"coverageRate":0.0709},{"memberCount":2,"allianceId":"500395207","allianceTag":"Hkr2","allianceCode":"Hkr2","allianceName":"柊連盟セカンド","allianceLeader":"wy.9035082403821","allianceLevel":2,"alliancePower":40600000,"alliancePowerText":"40.6M","allianceMemberCountShown":50,"allianceMemberMax":50,"allianceMemberText":"50/50","serverId":4077,"activitySummary":{"collectedMapMemberCount":2,"coreCount":0,"activeCount":2,"watchCount":0,"lowCount":0,"activeTotalCount":2,"totalPower":19190856,"corePowerSum":0,"activePowerSum":19190856,"corePowerRate":0,"activePowerRate":1,"top20PowerCount":0,"cumulative80PowerCount":0,"shownMemberCount":50,"shownMemberMax":50},"activeAllianceGrade":"INSUFFICIENT","activeAllianceScore":0,"activeAllianceReasons":["coverageRate=4%","coverageRate<10%","sample_too_small_for_alliance_grade"],"coverageRate":0.04},{"memberCount":2,"allianceId":"500396177","allianceTag":"l__1","allianceCode":"l__1","allianceName":"無言ポイ活a","allianceLeader":"sas","allianceLevel":3,"alliancePower":160000000,"alliancePowerText":"160M","allianceMemberCountShown":32,"allianceMemberMax":60,"allianceMemberText":"32/60","serverId":4077,"activitySummary":{"collectedMapMemberCount":2,"coreCount":1,"activeCount":1,"watchCount":0,"lowCount":0,"activeTotalCount":2,"totalPower":55137332,"corePowerSum":34065368,"activePowerSum":55137332,"corePowerRate":0.617828,"activePowerRate":1,"top20PowerCount":0,"cumulative80PowerCount":1,"shownMemberCount":32,"shownMemberMax":60},"activeAllianceGrade":"LOW","activeAllianceScore":0,"activeAllianceReasons":["coverageRate=6.25%","powerRate_ignored_due_to_low_coverage","power_too_concentrated"],"coverageRate":0.0625},{"memberCount":2,"allianceId":"500396213","allianceTag":"#hrg","allianceCode":"#hrg","allianceName":"風鈴月下","allianceLeader":"wy.9044874039277","allianceLevel":3,"alliancePower":57300000,"alliancePowerText":"57.3M","allianceMemberCountShown":57,"allianceMemberMax":90,"allianceMemberText":"57/90","serverId":4077,"activitySummary":{"collectedMapMemberCount":2,"coreCount":1,"activeCount":1,"watchCount":0,"lowCount":0,"activeTotalCount":2,"totalPower":24220592,"corePowerSum":13023545,"activePowerSum":24220592,"corePowerRate":0.537705,"activePowerRate":1,"top20PowerCount":0,"cumulative80PowerCount":1,"shownMemberCount":57,"shownMemberMax":90},"activeAllianceGrade":"INSUFFICIENT","activeAllianceScore":0,"activeAllianceReasons":["coverageRate=3.51%","coverageRate<10%","sample_too_small_for_alliance_grade"],"coverageRate":0.0351},{"memberCount":2,"allianceId":"500396250","allianceTag":"Ztmy","serverId":4077,"activitySummary":{"collectedMapMemberCount":2,"coreCount":0,"activeCount":1,"watchCount":1,"lowCount":0,"activeTotalCount":1,"totalPower":3447445,"corePowerSum":0,"activePowerSum":2150565,"corePowerRate":0,"activePowerRate":0.623814,"top20PowerCount":0,"cumulative80PowerCount":1,"shownMemberCount":null,"shownMemberMax":null},"activeAllianceGrade":"LOW","activeAllianceScore":0,"activeAllianceReasons":["coverageRate=100%","power_too_concentrated"],"coverageRate":1},{"memberCount":1,"allianceId":"500394844","allianceTag":"NOKU","serverId":4077,"activitySummary":{"collectedMapMemberCount":1,"coreCount":0,"activeCount":0,"watchCount":1,"lowCount":0,"activeTotalCount":0,"totalPower":8012107,"corePowerSum":0,"activePowerSum":0,"corePowerRate":0,"activePowerRate":0,"top20PowerCount":0,"cumulative80PowerCount":0,"shownMemberCount":null,"shownMemberMax":null},"activeAllianceGrade":"LOW","activeAllianceScore":0,"activeAllianceReasons":["coverageRate=100%"],"coverageRate":1},{"memberCount":1,"allianceId":"500394849","allianceTag":";%%x","serverId":4077,"activitySummary":{"collectedMapMemberCount":1,"coreCount":0,"activeCount":0,"watchCount":1,"lowCount":0,"activeTotalCount":0,"totalPower":2733085,"corePowerSum":0,"activePowerSum":0,"corePowerRate":0,"activePowerRate":0,"top20PowerCount":0,"cumulative80PowerCount":0,"shownMemberCount":null,"shownMemberMax":null},"activeAllianceGrade":"LOW","activeAllianceScore":0,"activeAllianceReasons":["coverageRate=100%"],"coverageRate":1},{"memberCount":1,"allianceId":"500395057","allianceTag":"l@cc","serverId":4077,"activitySummary":{"collectedMapMemberCount":1,"coreCount":0,"activeCount":0,"watchCount":1,"lowCount":0,"activeTotalCount":0,"totalPower":8558532,"corePowerSum":0,"activePowerSum":0,"corePowerRate":0,"activePowerRate":0,"top20PowerCount":0,"cumulative80PowerCount":0,"shownMemberCount":null,"shownMemberMax":null},"activeAllianceGrade":"LOW","activeAllianceScore":0,"activeAllianceReasons":["coverageRate=100%"],"coverageRate":1},{"memberCount":1,"allianceId":"500395775","allianceTag":"aeon","serverId":4077,"activitySummary":{"collectedMapMemberCount":1,"coreCount":0,"activeCount":0,"watchCount":1,"lowCount":0,"activeTotalCount":0,"totalPower":3452309,"corePowerSum":0,"activePowerSum":0,"corePowerRate":0,"activePowerRate":0,"top20PowerCount":0,"cumulative80PowerCount":0,"shownMemberCount":null,"shownMemberMax":null},"activeAllianceGrade":"LOW","activeAllianceScore":0,"activeAllianceReasons":["coverageRate=100%"],"coverageRate":1},{"memberCount":1,"allianceId":"500396627","allianceTag":"LVU.","serverId":4077,"activitySummary":{"collectedMapMemberCount":1,"coreCount":0,"activeCount":0,"watchCount":1,"lowCount":0,"activeTotalCount":0,"totalPower":124690,"corePowerSum":0,"activePowerSum":0,"corePowerRate":0,"activePowerRate":0,"top20PowerCount":0,"cumulative80PowerCount":0,"shownMemberCount":null,"shownMemberMax":null},"activeAllianceGrade":"LOW","activeAllianceScore":0,"activeAllianceReasons":["coverageRate=100%"],"coverageRate":1},{"memberCount":1,"allianceId":"500397233","allianceTag":"sho4","serverId":4077,"activitySummary":{"collectedMapMemberCount":1,"coreCount":0,"activeCount":0,"watchCount":1,"lowCount":0,"activeTotalCount":0,"totalPower":12820810,"corePowerSum":0,"activePowerSum":0,"corePowerRate":0,"activePowerRate":0,"top20PowerCount":0,"cumulative80PowerCount":0,"shownMemberCount":null,"shownMemberMax":null},"activeAllianceGrade":"LOW","activeAllianceScore":0,"activeAllianceReasons":["coverageRate=100%"],"coverageRate":1},{"memberCount":1,"allianceId":"500402635","allianceTag":"p01t","serverId":4077,"activitySummary":{"collectedMapMemberCount":1,"coreCount":0,"activeCount":0,"watchCount":1,"lowCount":0,"activeTotalCount":0,"totalPower":985555,"corePowerSum":0,"activePowerSum":0,"corePowerRate":0,"activePowerRate":0,"top20PowerCount":0,"cumulative80PowerCount":0,"shownMemberCount":null,"shownMemberMax":null},"activeAllianceGrade":"LOW","activeAllianceScore":0,"activeAllianceReasons":["coverageRate=100%"],"coverageRate":1},{"memberCount":1,"allianceId":"500433110","allianceTag":"stpc","serverId":4077,"activitySummary":{"collectedMapMemberCount":1,"coreCount":0,"activeCount":0,"watchCount":1,"lowCount":0,"activeTotalCount":0,"totalPower":106310,"corePowerSum":0,"activePowerSum":0,"corePowerRate":0,"activePowerRate":0,"top20PowerCount":0,"cumulative80PowerCount":0,"shownMemberCount":null,"shownMemberMax":null},"activeAllianceGrade":"LOW","activeAllianceScore":0,"activeAllianceReasons":["coverageRate=100%"],"coverageRate":1}]}